{
  "2020": [
    {
      "Canton ID": 17,
      "Canton": "SG",
      "SFO Commune ID": 3251,
      "Commune": "Altstätten",
      "Canton_1": 115,
      "Commune_1": 122,
      "Church, Protestant": 28,
      "Church, Roman Catholic": 19,
      "Church, Christian Catholic": 24,
      "Canton_2": 115,
      "Commune_2": 122,
      "Church, Protestant_1": 28,
      "Church, Roman Catholic_1": 19,
      "Church, Christian Catholic_1": 24,
      "Canton_3": 302,
      "Commune_3": 0,
      "Church": 0,
      "Canton_4": 302,
      "Commune_4": 0,
      "Church_1": 0
    },
    {
      "Canton ID": 17,
      "Canton": "SG",
      "SFO Commune ID": 3311,
      "Commune": "Amden",
      "Canton_1": 115,
      "Commune_1": 120,
      "Church, Protestant": 26,
      "Church, Roman Catholic": 25,
      "Church, Christian Catholic": 24,
      "Canton_2": 115,
      "Commune_2": 120,
      "Church, Protestant_1": 26,
      "Church, Roman Catholic_1": 25,
      "Church, Christian Catholic_1": 24,
      "Canton_3": 302,
      "Commune_3": 0,
      "Church": 0,
      "Canton_4": 302,
      "Commune_4": 0,
      "Church_1": 0
    },
    {
      "Canton ID": 17,
      "Canton": "SG",
      "SFO Commune ID": 3441,
      "Commune": "Andwil (SG)",
      "Canton_1": 115,
      "Commune_1": 118,
      "Church, Protestant": 23,
      "Church, Roman Catholic": 26,
      "Church, Christian Catholic": 24,
      "Canton_2": 115,
      "Commune_2": 118,
      "Church, Protestant_1": 23,
      "Church, Roman Catholic_1": 26,
      "Church, Christian Catholic_1": 24,
      "Canton_3": 302,
      "Commune_3": 0,
      "Church": 0,
      "Canton_4": 302,
      "Commune_4": 0,
      "Church_1": 0
    },
    {
      "Canton ID": 17,
      "Canton": "SG",
      "SFO Commune ID": 3231,
      "Commune": "Au (SG)",
      "Canton_1": 115,
      "Commune_1": 87,
      "Church, Protestant": 25,
      "Church, Roman Catholic": 21,
      "Church, Christian Catholic": 24,
      "Canton_2": 115,
      "Commune_2": 87,
      "Church, Protestant_1": 25,
      "Church, Roman Catholic_1": 21,
      "Church, Christian Catholic_1": 24,
      "Canton_3": 302,
      "Commune_3": 0,
      "Church": 0,
      "Canton_4": 302,
      "Commune_4": 0,
      "Church_1": 0
    },
    {
      "Canton ID": 17,
      "Canton": "SG",
      "SFO Commune ID": 3291,
      "Commune": "Bad Ragaz",
      "Canton_1": 115,
      "Commune_1": 92,
      "Church, Protestant": 28,
      "Church, Roman Catholic": 17,
      "Church, Christian Catholic": 24,
      "Canton_2": 115,
      "Commune_2": 92,
      "Church, Protestant_1": 28,
      "Church, Roman Catholic_1": 17,
      "Church, Christian Catholic_1": 24,
      "Canton_3": 302,
      "Commune_3": 0,
      "Church": 0,
      "Canton_4": 302,
      "Commune_4": 0,
      "Church_1": 0
    },
    {
      "Canton ID": 17,
      "Canton": "SG",
      "SFO Commune ID": 3232,
      "Commune": "Balgach",
      "Canton_1": 115,
      "Commune_1": 72,
      "Church, Protestant": 25,
      "Church, Roman Catholic": 19,
      "Church, Christian Catholic": 24,
      "Canton_2": 115,
      "Commune_2": 72,
      "Church, Protestant_1": 25,
      "Church, Roman Catholic_1": 19,
      "Church, Christian Catholic_1": 24,
      "Canton_3": 302,
      "Commune_3": 0,
      "Church": 0,
      "Canton_4": 302,
      "Commune_4": 0,
      "Church_1": 0
    },
    {
      "Canton ID": 17,
      "Canton": "SG",
      "SFO Commune ID": 3312,
      "Commune": "Benken (SG)",
      "Canton_1": 115,
      "Commune_1": 130,
      "Church, Protestant": 24,
      "Church, Roman Catholic": 24,
      "Church, Christian Catholic": 24,
      "Canton_2": 115,
      "Commune_2": 130,
      "Church, Protestant_1": 24,
      "Church, Roman Catholic_1": 24,
      "Church, Christian Catholic_1": 24,
      "Canton_3": 302,
      "Commune_3": 0,
      "Church": 0,
      "Canton_4": 302,
      "Commune_4": 0,
      "Church_1": 0
    },
    {
      "Canton ID": 17,
      "Canton": "SG",
      "SFO Commune ID": 3211,
      "Commune": "Berg (SG)",
      "Canton_1": 115,
      "Commune_1": 136,
      "Church, Protestant": 18,
      "Church, Roman Catholic": 24,
      "Church, Christian Catholic": 24,
      "Canton_2": 115,
      "Commune_2": 136,
      "Church, Protestant_1": 18,
      "Church, Roman Catholic_1": 24,
      "Church, Christian Catholic_1": 24,
      "Canton_3": 302,
      "Commune_3": 0,
      "Church": 0,
      "Canton_4": 302,
      "Commune_4": 0,
      "Church_1": 0
    },
    {
      "Canton ID": 17,
      "Canton": "SG",
      "SFO Commune ID": 3233,
      "Commune": "Berneck",
      "Canton_1": 115,
      "Commune_1": 97,
      "Church, Protestant": 25,
      "Church, Roman Catholic": 21,
      "Church, Christian Catholic": 24,
      "Canton_2": 115,
      "Commune_2": 97,
      "Church, Protestant_1": 25,
      "Church, Roman Catholic_1": 21,
      "Church, Christian Catholic_1": 24,
      "Canton_3": 302,
      "Commune_3": 0,
      "Church": 0,
      "Canton_4": 302,
      "Commune_4": 0,
      "Church_1": 0
    },
    {
      "Canton ID": 17,
      "Canton": "SG",
      "SFO Commune ID": 3271,
      "Commune": "Buchs (SG)",
      "Canton_1": 115,
      "Commune_1": 118,
      "Church, Protestant": 27,
      "Church, Roman Catholic": 18,
      "Church, Christian Catholic": 24,
      "Canton_2": 115,
      "Commune_2": 118,
      "Church, Protestant_1": 27,
      "Church, Roman Catholic_1": 18,
      "Church, Christian Catholic_1": 24,
      "Canton_3": 302,
      "Commune_3": 0,
      "Church": 0,
      "Canton_4": 302,
      "Commune_4": 0,
      "Church_1": 0
    },
    {
      "Canton ID": 17,
      "Canton": "SG",
      "SFO Commune ID": 3395,
      "Commune": "Bütschwil-Ganterschwil",
      "Canton_1": 115,
      "Commune_1": 129,
      "Church, Protestant": 28,
      "Church, Roman Catholic": 25,
      "Church, Christian Catholic": 24,
      "Canton_2": 115,
      "Commune_2": 129,
      "Church, Protestant_1": 28,
      "Church, Roman Catholic_1": 25,
      "Church, Christian Catholic_1": 24,
      "Canton_3": 302,
      "Commune_3": 0,
      "Church": 0,
      "Canton_4": 302,
      "Commune_4": 0,
      "Church_1": 0
    },
    {
      "Canton ID": 17,
      "Canton": "SG",
      "SFO Commune ID": 3401,
      "Commune": "Degersheim",
      "Canton_1": 115,
      "Commune_1": 156,
      "Church, Protestant": 28,
      "Church, Roman Catholic": 25,
      "Church, Christian Catholic": 24,
      "Canton_2": 115,
      "Commune_2": 156,
      "Church, Protestant_1": 28,
      "Church, Roman Catholic_1": 25,
      "Church, Christian Catholic_1": 24,
      "Canton_3": 302,
      "Commune_3": 0,
      "Church": 0,
      "Canton_4": 302,
      "Commune_4": 0,
      "Church_1": 0
    },
    {
      "Canton ID": 17,
      "Canton": "SG",
      "SFO Commune ID": 3234,
      "Commune": "Diepoldsau",
      "Canton_1": 115,
      "Commune_1": 89,
      "Church, Protestant": 24,
      "Church, Roman Catholic": 21,
      "Church, Christian Catholic": 24,
      "Canton_2": 115,
      "Commune_2": 89,
      "Church, Protestant_1": 24,
      "Church, Roman Catholic_1": 21,
      "Church, Christian Catholic_1": 24,
      "Canton_3": 302,
      "Commune_3": 0,
      "Church": 0,
      "Canton_4": 302,
      "Commune_4": 0,
      "Church_1": 0
    },
    {
      "Canton ID": 17,
      "Canton": "SG",
      "SFO Commune ID": 3352,
      "Commune": "Ebnat-Kappel",
      "Canton_1": 115,
      "Commune_1": 139,
      "Church, Protestant": 28,
      "Church, Roman Catholic": 27,
      "Church, Christian Catholic": 24,
      "Canton_2": 115,
      "Commune_2": 139,
      "Church, Protestant_1": 28,
      "Church, Roman Catholic_1": 27,
      "Church, Christian Catholic_1": 24,
      "Canton_3": 302,
      "Commune_3": 0,
      "Church": 0,
      "Canton_4": 302,
      "Commune_4": 0,
      "Church_1": 0
    },
    {
      "Canton ID": 17,
      "Canton": "SG",
      "SFO Commune ID": 3212,
      "Commune": "Eggersriet",
      "Canton_1": 115,
      "Commune_1": 125,
      "Church, Protestant": 24,
      "Church, Roman Catholic": 26,
      "Church, Christian Catholic": 24,
      "Canton_2": 115,
      "Commune_2": 125,
      "Church, Protestant_1": 24,
      "Church, Roman Catholic_1": 26,
      "Church, Christian Catholic_1": 24,
      "Canton_3": 302,
      "Commune_3": 0,
      "Church": 0,
      "Canton_4": 302,
      "Commune_4": 0,
      "Church_1": 0
    },
    {
      "Canton ID": 17,
      "Canton": "SG",
      "SFO Commune ID": 3252,
      "Commune": "Eichberg",
      "Canton_1": 115,
      "Commune_1": 119,
      "Church, Protestant": 28,
      "Church, Roman Catholic": 19,
      "Church, Christian Catholic": 24,
      "Canton_2": 115,
      "Commune_2": 119,
      "Church, Protestant_1": 28,
      "Church, Roman Catholic_1": 19,
      "Church, Christian Catholic_1": 24,
      "Canton_3": 302,
      "Commune_3": 0,
      "Church": 0,
      "Canton_4": 302,
      "Commune_4": 0,
      "Church_1": 0
    },
    {
      "Canton ID": 17,
      "Canton": "SG",
      "SFO Commune ID": 3342,
      "Commune": "Eschenbach (SG)",
      "Canton_1": 115,
      "Commune_1": 121,
      "Church, Protestant": 24,
      "Church, Roman Catholic": 24,
      "Church, Christian Catholic": 24,
      "Canton_2": 115,
      "Commune_2": 121,
      "Church, Protestant_1": 24,
      "Church, Roman Catholic_1": 24,
      "Church, Christian Catholic_1": 24,
      "Canton_3": 302,
      "Commune_3": 0,
      "Church": 0,
      "Canton_4": 302,
      "Commune_4": 0,
      "Church_1": 0
    },
    {
      "Canton ID": 17,
      "Canton": "SG",
      "SFO Commune ID": 3402,
      "Commune": "Flawil",
      "Canton_1": 115,
      "Commune_1": 133,
      "Church, Protestant": 27,
      "Church, Roman Catholic": 25,
      "Church, Christian Catholic": 24,
      "Canton_2": 115,
      "Commune_2": 133,
      "Church, Protestant_1": 27,
      "Church, Roman Catholic_1": 25,
      "Church, Christian Catholic_1": 24,
      "Canton_3": 302,
      "Commune_3": 0,
      "Church": 0,
      "Canton_4": 302,
      "Commune_4": 0,
      "Church_1": 0
    },
    {
      "Canton ID": 17,
      "Canton": "SG",
      "SFO Commune ID": 3292,
      "Commune": "Flums",
      "Canton_1": 115,
      "Commune_1": 130,
      "Church, Protestant": 24,
      "Church, Roman Catholic": 26,
      "Church, Christian Catholic": 24,
      "Canton_2": 115,
      "Commune_2": 130,
      "Church, Protestant_1": 24,
      "Church, Roman Catholic_1": 26,
      "Church, Christian Catholic_1": 24,
      "Canton_3": 302,
      "Commune_3": 0,
      "Church": 0,
      "Canton_4": 302,
      "Commune_4": 0,
      "Church_1": 0
    },
    {
      "Canton ID": 17,
      "Canton": "SG",
      "SFO Commune ID": 3442,
      "Commune": "Gaiserwald",
      "Canton_1": 115,
      "Commune_1": 107,
      "Church, Protestant": 21,
      "Church, Roman Catholic": 21,
      "Church, Christian Catholic": 24,
      "Canton_2": 115,
      "Commune_2": 107,
      "Church, Protestant_1": 21,
      "Church, Roman Catholic_1": 21,
      "Church, Christian Catholic_1": 24,
      "Canton_3": 302,
      "Commune_3": 0,
      "Church": 0,
      "Canton_4": 302,
      "Commune_4": 0,
      "Church_1": 0
    },
    {
      "Canton ID": 17,
      "Canton": "SG",
      "SFO Commune ID": 3272,
      "Commune": "Gams",
      "Canton_1": 115,
      "Commune_1": 125,
      "Church, Protestant": 27,
      "Church, Roman Catholic": 24,
      "Church, Christian Catholic": 24,
      "Canton_2": 115,
      "Commune_2": 125,
      "Church, Protestant_1": 27,
      "Church, Roman Catholic_1": 24,
      "Church, Christian Catholic_1": 24,
      "Canton_3": 302,
      "Commune_3": 0,
      "Church": 0,
      "Canton_4": 302,
      "Commune_4": 0,
      "Church_1": 0
    },
    {
      "Canton ID": 17,
      "Canton": "SG",
      "SFO Commune ID": 3213,
      "Commune": "Goldach",
      "Canton_1": 115,
      "Commune_1": 98,
      "Church, Protestant": 23,
      "Church, Roman Catholic": 24,
      "Church, Christian Catholic": 24,
      "Canton_2": 115,
      "Commune_2": 98,
      "Church, Protestant_1": 23,
      "Church, Roman Catholic_1": 24,
      "Church, Christian Catholic_1": 24,
      "Canton_3": 302,
      "Commune_3": 0,
      "Church": 0,
      "Canton_4": 302,
      "Commune_4": 0,
      "Church_1": 0
    },
    {
      "Canton ID": 17,
      "Canton": "SG",
      "SFO Commune ID": 3341,
      "Commune": "Gommiswald",
      "Canton_1": 115,
      "Commune_1": 116,
      "Church, Protestant": 24,
      "Church, Roman Catholic": 24,
      "Church, Christian Catholic": 24,
      "Canton_2": 115,
      "Commune_2": 116,
      "Church, Protestant_1": 24,
      "Church, Roman Catholic_1": 24,
      "Church, Christian Catholic_1": 24,
      "Canton_3": 302,
      "Commune_3": 0,
      "Church": 0,
      "Canton_4": 302,
      "Commune_4": 0,
      "Church_1": 0
    },
    {
      "Canton ID": 17,
      "Canton": "SG",
      "SFO Commune ID": 3443,
      "Commune": "Gossau (SG)",
      "Canton_1": 115,
      "Commune_1": 116,
      "Church, Protestant": 23,
      "Church, Roman Catholic": 23,
      "Church, Christian Catholic": 24,
      "Canton_2": 115,
      "Commune_2": 116,
      "Church, Protestant_1": 23,
      "Church, Roman Catholic_1": 23,
      "Church, Christian Catholic_1": 24,
      "Canton_3": 302,
      "Commune_3": 0,
      "Church": 0,
      "Canton_4": 302,
      "Commune_4": 0,
      "Church_1": 0
    },
    {
      "Canton ID": 17,
      "Canton": "SG",
      "SFO Commune ID": 3273,
      "Commune": "Grabs",
      "Canton_1": 115,
      "Commune_1": 110,
      "Church, Protestant": 27,
      "Church, Roman Catholic": 18,
      "Church, Christian Catholic": 24,
      "Canton_2": 115,
      "Commune_2": 110,
      "Church, Protestant_1": 27,
      "Church, Roman Catholic_1": 18,
      "Church, Christian Catholic_1": 24,
      "Canton_3": 302,
      "Commune_3": 0,
      "Church": 0,
      "Canton_4": 302,
      "Commune_4": 0,
      "Church_1": 0
    },
    {
      "Canton ID": 17,
      "Canton": "SG",
      "SFO Commune ID": 3372,
      "Commune": "Hemberg",
      "Canton_1": 115,
      "Commune_1": 138,
      "Church, Protestant": 28,
      "Church, Roman Catholic": 26,
      "Church, Christian Catholic": 24,
      "Canton_2": 115,
      "Commune_2": 138,
      "Church, Protestant_1": 28,
      "Church, Roman Catholic_1": 26,
      "Church, Christian Catholic_1": 24,
      "Canton_3": 302,
      "Commune_3": 0,
      "Church": 0,
      "Canton_4": 302,
      "Commune_4": 0,
      "Church_1": 0
    },
    {
      "Canton ID": 17,
      "Canton": "SG",
      "SFO Commune ID": 3201,
      "Commune": "Häggenschwil",
      "Canton_1": 115,
      "Commune_1": 119,
      "Church, Protestant": 18,
      "Church, Roman Catholic": 24,
      "Church, Christian Catholic": 24,
      "Canton_2": 115,
      "Commune_2": 119,
      "Church, Protestant_1": 18,
      "Church, Roman Catholic_1": 24,
      "Church, Christian Catholic_1": 24,
      "Canton_3": 302,
      "Commune_3": 0,
      "Church": 0,
      "Canton_4": 302,
      "Commune_4": 0,
      "Church_1": 0
    },
    {
      "Canton ID": 17,
      "Canton": "SG",
      "SFO Commune ID": 3405,
      "Commune": "Jonschwil",
      "Canton_1": 115,
      "Commune_1": 127,
      "Church, Protestant": 25,
      "Church, Roman Catholic": 26,
      "Church, Christian Catholic": 24,
      "Canton_2": 115,
      "Commune_2": 127,
      "Church, Protestant_1": 25,
      "Church, Roman Catholic_1": 26,
      "Church, Christian Catholic_1": 24,
      "Canton_3": 302,
      "Commune_3": 0,
      "Church": 0,
      "Canton_4": 302,
      "Commune_4": 0,
      "Church_1": 0
    },
    {
      "Canton ID": 17,
      "Canton": "SG",
      "SFO Commune ID": 3313,
      "Commune": "Kaltbrunn",
      "Canton_1": 115,
      "Commune_1": 106,
      "Church, Protestant": 24,
      "Church, Roman Catholic": 21,
      "Church, Christian Catholic": 24,
      "Canton_2": 115,
      "Commune_2": 106,
      "Church, Protestant_1": 24,
      "Church, Roman Catholic_1": 21,
      "Church, Christian Catholic_1": 24,
      "Canton_3": 302,
      "Commune_3": 0,
      "Church": 0,
      "Canton_4": 302,
      "Commune_4": 0,
      "Church_1": 0
    },
    {
      "Canton ID": 17,
      "Canton": "SG",
      "SFO Commune ID": 3392,
      "Commune": "Kirchberg (SG)",
      "Canton_1": 115,
      "Commune_1": 133,
      "Church, Protestant": 26,
      "Church, Roman Catholic": 24,
      "Church, Christian Catholic": 24,
      "Canton_2": 115,
      "Commune_2": 133,
      "Church, Protestant_1": 26,
      "Church, Roman Catholic_1": 24,
      "Church, Christian Catholic_1": 24,
      "Canton_3": 302,
      "Commune_3": 0,
      "Church": 0,
      "Canton_4": 302,
      "Commune_4": 0,
      "Church_1": 0
    },
    {
      "Canton ID": 17,
      "Canton": "SG",
      "SFO Commune ID": 3374,
      "Commune": "Lichtensteig",
      "Canton_1": 115,
      "Commune_1": 137,
      "Church, Protestant": 28,
      "Church, Roman Catholic": 27,
      "Church, Christian Catholic": 24,
      "Canton_2": 115,
      "Commune_2": 137,
      "Church, Protestant_1": 28,
      "Church, Roman Catholic_1": 27,
      "Church, Christian Catholic_1": 24,
      "Canton_3": 302,
      "Commune_3": 0,
      "Church": 0,
      "Canton_4": 302,
      "Commune_4": 0,
      "Church_1": 0
    },
    {
      "Canton ID": 17,
      "Canton": "SG",
      "SFO Commune ID": 3393,
      "Commune": "Lütisburg",
      "Canton_1": 115,
      "Commune_1": 125,
      "Church, Protestant": 28,
      "Church, Roman Catholic": 24,
      "Church, Christian Catholic": 24,
      "Canton_2": 115,
      "Commune_2": 125,
      "Church, Protestant_1": 28,
      "Church, Roman Catholic_1": 24,
      "Church, Christian Catholic_1": 24,
      "Canton_3": 302,
      "Commune_3": 0,
      "Church": 0,
      "Canton_4": 302,
      "Commune_4": 0,
      "Church_1": 0
    },
    {
      "Canton ID": 17,
      "Canton": "SG",
      "SFO Commune ID": 3253,
      "Commune": "Marbach (SG)",
      "Canton_1": 115,
      "Commune_1": 115,
      "Church, Protestant": 28,
      "Church, Roman Catholic": 26,
      "Church, Christian Catholic": 24,
      "Canton_2": 115,
      "Commune_2": 115,
      "Church, Protestant_1": 28,
      "Church, Roman Catholic_1": 26,
      "Church, Christian Catholic_1": 24,
      "Canton_3": 302,
      "Commune_3": 0,
      "Church": 0,
      "Canton_4": 302,
      "Commune_4": 0,
      "Church_1": 0
    },
    {
      "Canton ID": 17,
      "Canton": "SG",
      "SFO Commune ID": 3293,
      "Commune": "Mels",
      "Canton_1": 115,
      "Commune_1": 133,
      "Church, Protestant": 22,
      "Church, Roman Catholic": 22,
      "Church, Christian Catholic": 24,
      "Canton_2": 115,
      "Commune_2": 133,
      "Church, Protestant_1": 22,
      "Church, Roman Catholic_1": 22,
      "Church, Christian Catholic_1": 24,
      "Canton_3": 302,
      "Commune_3": 0,
      "Church": 0,
      "Canton_4": 302,
      "Commune_4": 0,
      "Church_1": 0
    },
    {
      "Canton ID": 17,
      "Canton": "SG",
      "SFO Commune ID": 3394,
      "Commune": "Mosnang",
      "Canton_1": 115,
      "Commune_1": 137,
      "Church, Protestant": 28,
      "Church, Roman Catholic": 26,
      "Church, Christian Catholic": 24,
      "Canton_2": 115,
      "Commune_2": 137,
      "Church, Protestant_1": 28,
      "Church, Roman Catholic_1": 26,
      "Church, Christian Catholic_1": 24,
      "Canton_3": 302,
      "Commune_3": 0,
      "Church": 0,
      "Canton_4": 302,
      "Commune_4": 0,
      "Church_1": 0
    },
    {
      "Canton ID": 17,
      "Canton": "SG",
      "SFO Commune ID": 3202,
      "Commune": "Muolen",
      "Canton_1": 115,
      "Commune_1": 129,
      "Church, Protestant": 20,
      "Church, Roman Catholic": 24,
      "Church, Christian Catholic": 24,
      "Canton_2": 115,
      "Commune_2": 129,
      "Church, Protestant_1": 20,
      "Church, Roman Catholic_1": 24,
      "Church, Christian Catholic_1": 24,
      "Canton_3": 302,
      "Commune_3": 0,
      "Church": 0,
      "Canton_4": 302,
      "Commune_4": 0,
      "Church_1": 0
    },
    {
      "Canton ID": 17,
      "Canton": "SG",
      "SFO Commune ID": 3214,
      "Commune": "Mörschwil",
      "Canton_1": 115,
      "Commune_1": 75,
      "Church, Protestant": 23,
      "Church, Roman Catholic": 16,
      "Church, Christian Catholic": 24,
      "Canton_2": 115,
      "Commune_2": 75,
      "Church, Protestant_1": 23,
      "Church, Roman Catholic_1": 16,
      "Church, Christian Catholic_1": 24,
      "Canton_3": 302,
      "Commune_3": 0,
      "Church": 0,
      "Canton_4": 302,
      "Commune_4": 0,
      "Church_1": 0
    },
    {
      "Canton ID": 17,
      "Canton": "SG",
      "SFO Commune ID": 3378,
      "Commune": "Neckertal",
      "Canton_1": 115,
      "Commune_1": 132,
      "Church, Protestant": 28,
      "Church, Roman Catholic": 24,
      "Church, Christian Catholic": 24,
      "Canton_2": 115,
      "Commune_2": 132,
      "Church, Protestant_1": 28,
      "Church, Roman Catholic_1": 24,
      "Church, Christian Catholic_1": 24,
      "Canton_3": 302,
      "Commune_3": 0,
      "Church": 0,
      "Canton_4": 302,
      "Commune_4": 0,
      "Church_1": 0
    },
    {
      "Canton ID": 17,
      "Canton": "SG",
      "SFO Commune ID": 3360,
      "Commune": "Nesslau",
      "Canton_1": 115,
      "Commune_1": 125,
      "Church, Protestant": 28,
      "Church, Roman Catholic": 26,
      "Church, Christian Catholic": 24,
      "Canton_2": 115,
      "Commune_2": 125,
      "Church, Protestant_1": 28,
      "Church, Roman Catholic_1": 26,
      "Church, Christian Catholic_1": 24,
      "Canton_3": 302,
      "Commune_3": 0,
      "Church": 0,
      "Canton_4": 302,
      "Commune_4": 0,
      "Church_1": 0
    },
    {
      "Canton ID": 17,
      "Canton": "SG",
      "SFO Commune ID": 3422,
      "Commune": "Niederbüren",
      "Canton_1": 115,
      "Commune_1": 129,
      "Church, Protestant": 28,
      "Church, Roman Catholic": 25,
      "Church, Christian Catholic": 24,
      "Canton_2": 115,
      "Commune_2": 129,
      "Church, Protestant_1": 28,
      "Church, Roman Catholic_1": 25,
      "Church, Christian Catholic_1": 24,
      "Canton_3": 302,
      "Commune_3": 0,
      "Church": 0,
      "Canton_4": 302,
      "Commune_4": 0,
      "Church_1": 0
    },
    {
      "Canton ID": 17,
      "Canton": "SG",
      "SFO Commune ID": 3423,
      "Commune": "Niederhelfenschwil",
      "Canton_1": 115,
      "Commune_1": 114,
      "Church, Protestant": 32,
      "Church, Roman Catholic": 24,
      "Church, Christian Catholic": 24,
      "Canton_2": 115,
      "Commune_2": 114,
      "Church, Protestant_1": 32,
      "Church, Roman Catholic_1": 24,
      "Church, Christian Catholic_1": 24,
      "Canton_3": 302,
      "Commune_3": 0,
      "Church": 0,
      "Canton_4": 302,
      "Commune_4": 0,
      "Church_1": 0
    },
    {
      "Canton ID": 17,
      "Canton": "SG",
      "SFO Commune ID": 3424,
      "Commune": "Oberbüren",
      "Canton_1": 115,
      "Commune_1": 100,
      "Church, Protestant": 25,
      "Church, Roman Catholic": 29,
      "Church, Christian Catholic": 24,
      "Canton_2": 115,
      "Commune_2": 100,
      "Church, Protestant_1": 25,
      "Church, Roman Catholic_1": 29,
      "Church, Christian Catholic_1": 24,
      "Canton_3": 302,
      "Commune_3": 0,
      "Church": 0,
      "Canton_4": 302,
      "Commune_4": 0,
      "Church_1": 0
    },
    {
      "Canton ID": 17,
      "Canton": "SG",
      "SFO Commune ID": 3375,
      "Commune": "Oberhelfenschwil",
      "Canton_1": 115,
      "Commune_1": 134,
      "Church, Protestant": 28,
      "Church, Roman Catholic": 24,
      "Church, Christian Catholic": 24,
      "Canton_2": 115,
      "Commune_2": 134,
      "Church, Protestant_1": 28,
      "Church, Roman Catholic_1": 24,
      "Church, Christian Catholic_1": 24,
      "Canton_3": 302,
      "Commune_3": 0,
      "Church": 0,
      "Canton_4": 302,
      "Commune_4": 0,
      "Church_1": 0
    },
    {
      "Canton ID": 17,
      "Canton": "SG",
      "SFO Commune ID": 3254,
      "Commune": "Oberriet (SG)",
      "Canton_1": 115,
      "Commune_1": 102,
      "Church, Protestant": 28,
      "Church, Roman Catholic": 25,
      "Church, Christian Catholic": 24,
      "Canton_2": 115,
      "Commune_2": 102,
      "Church, Protestant_1": 28,
      "Church, Roman Catholic_1": 25,
      "Church, Christian Catholic_1": 24,
      "Canton_3": 302,
      "Commune_3": 0,
      "Church": 0,
      "Canton_4": 302,
      "Commune_4": 0,
      "Church_1": 0
    },
    {
      "Canton ID": 17,
      "Canton": "SG",
      "SFO Commune ID": 3407,
      "Commune": "Oberuzwil",
      "Canton_1": 115,
      "Commune_1": 125,
      "Church, Protestant": 25,
      "Church, Roman Catholic": 24,
      "Church, Christian Catholic": 24,
      "Canton_2": 115,
      "Commune_2": 125,
      "Church, Protestant_1": 25,
      "Church, Roman Catholic_1": 24,
      "Church, Christian Catholic_1": 24,
      "Canton_3": 302,
      "Commune_3": 0,
      "Church": 0,
      "Canton_4": 302,
      "Commune_4": 0,
      "Church_1": 0
    },
    {
      "Canton ID": 17,
      "Canton": "SG",
      "SFO Commune ID": 3294,
      "Commune": "Pfäfers",
      "Canton_1": 115,
      "Commune_1": 145,
      "Church, Protestant": 28,
      "Church, Roman Catholic": 25,
      "Church, Christian Catholic": 24,
      "Canton_2": 115,
      "Commune_2": 145,
      "Church, Protestant_1": 28,
      "Church, Roman Catholic_1": 25,
      "Church, Christian Catholic_1": 24,
      "Canton_3": 302,
      "Commune_3": 0,
      "Church": 0,
      "Canton_4": 302,
      "Commune_4": 0,
      "Church_1": 0
    },
    {
      "Canton ID": 17,
      "Canton": "SG",
      "SFO Commune ID": 3295,
      "Commune": "Quarten",
      "Canton_1": 115,
      "Commune_1": 115,
      "Church, Protestant": 24,
      "Church, Roman Catholic": 25,
      "Church, Christian Catholic": 24,
      "Canton_2": 115,
      "Commune_2": 115,
      "Church, Protestant_1": 24,
      "Church, Roman Catholic_1": 25,
      "Church, Christian Catholic_1": 24,
      "Canton_3": 302,
      "Commune_3": 0,
      "Church": 0,
      "Canton_4": 302,
      "Commune_4": 0,
      "Church_1": 0
    },
    {
      "Canton ID": 17,
      "Canton": "SG",
      "SFO Commune ID": 3340,
      "Commune": "Rapperswil-Jona",
      "Canton_1": 115,
      "Commune_1": 76,
      "Church, Protestant": 20,
      "Church, Roman Catholic": 19,
      "Church, Christian Catholic": 24,
      "Canton_2": 115,
      "Commune_2": 76,
      "Church, Protestant_1": 20,
      "Church, Roman Catholic_1": 19,
      "Church, Christian Catholic_1": 24,
      "Canton_3": 302,
      "Commune_3": 0,
      "Church": 0,
      "Canton_4": 302,
      "Commune_4": 0,
      "Church_1": 0
    },
    {
      "Canton ID": 17,
      "Canton": "SG",
      "SFO Commune ID": 3255,
      "Commune": "Rebstein",
      "Canton_1": 115,
      "Commune_1": 109,
      "Church, Protestant": 28,
      "Church, Roman Catholic": 29,
      "Church, Christian Catholic": 24,
      "Canton_2": 115,
      "Commune_2": 109,
      "Church, Protestant_1": 28,
      "Church, Roman Catholic_1": 29,
      "Church, Christian Catholic_1": 24,
      "Canton_3": 302,
      "Commune_3": 0,
      "Church": 0,
      "Canton_4": 302,
      "Commune_4": 0,
      "Church_1": 0
    },
    {
      "Canton ID": 17,
      "Canton": "SG",
      "SFO Commune ID": 3235,
      "Commune": "Rheineck",
      "Canton_1": 115,
      "Commune_1": 119,
      "Church, Protestant": 28,
      "Church, Roman Catholic": 24,
      "Church, Christian Catholic": 24,
      "Canton_2": 115,
      "Commune_2": 119,
      "Church, Protestant_1": 28,
      "Church, Roman Catholic_1": 24,
      "Church, Christian Catholic_1": 24,
      "Canton_3": 302,
      "Commune_3": 0,
      "Church": 0,
      "Canton_4": 302,
      "Commune_4": 0,
      "Church_1": 0
    },
    {
      "Canton ID": 17,
      "Canton": "SG",
      "SFO Commune ID": 3215,
      "Commune": "Rorschach",
      "Canton_1": 115,
      "Commune_1": 134,
      "Church, Protestant": 28,
      "Church, Roman Catholic": 24,
      "Church, Christian Catholic": 24,
      "Canton_2": 115,
      "Commune_2": 134,
      "Church, Protestant_1": 28,
      "Church, Roman Catholic_1": 24,
      "Church, Christian Catholic_1": 24,
      "Canton_3": 302,
      "Commune_3": 0,
      "Church": 0,
      "Canton_4": 302,
      "Commune_4": 0,
      "Church_1": 0
    },
    {
      "Canton ID": 17,
      "Canton": "SG",
      "SFO Commune ID": 3216,
      "Commune": "Rorschacherberg",
      "Canton_1": 115,
      "Commune_1": 96,
      "Church, Protestant": 28,
      "Church, Roman Catholic": 24,
      "Church, Christian Catholic": 24,
      "Canton_2": 115,
      "Commune_2": 96,
      "Church, Protestant_1": 28,
      "Church, Roman Catholic_1": 24,
      "Church, Christian Catholic_1": 24,
      "Canton_3": 302,
      "Commune_3": 0,
      "Church": 0,
      "Canton_4": 302,
      "Commune_4": 0,
      "Church_1": 0
    },
    {
      "Canton ID": 17,
      "Canton": "SG",
      "SFO Commune ID": 3256,
      "Commune": "Rüthi (SG)",
      "Canton_1": 115,
      "Commune_1": 119,
      "Church, Protestant": 28,
      "Church, Roman Catholic": 26,
      "Church, Christian Catholic": 24,
      "Canton_2": 115,
      "Commune_2": 119,
      "Church, Protestant_1": 28,
      "Church, Roman Catholic_1": 26,
      "Church, Christian Catholic_1": 24,
      "Canton_3": 302,
      "Commune_3": 0,
      "Church": 0,
      "Canton_4": 302,
      "Commune_4": 0,
      "Church_1": 0
    },
    {
      "Canton ID": 17,
      "Canton": "SG",
      "SFO Commune ID": 3296,
      "Commune": "Sargans",
      "Canton_1": 115,
      "Commune_1": 142,
      "Church, Protestant": 22,
      "Church, Roman Catholic": 21,
      "Church, Christian Catholic": 24,
      "Canton_2": 115,
      "Commune_2": 142,
      "Church, Protestant_1": 22,
      "Church, Roman Catholic_1": 21,
      "Church, Christian Catholic_1": 24,
      "Canton_3": 302,
      "Commune_3": 0,
      "Church": 0,
      "Canton_4": 302,
      "Commune_4": 0,
      "Church_1": 0
    },
    {
      "Canton ID": 17,
      "Canton": "SG",
      "SFO Commune ID": 3338,
      "Commune": "Schmerikon",
      "Canton_1": 115,
      "Commune_1": 116,
      "Church, Protestant": 24,
      "Church, Roman Catholic": 24,
      "Church, Christian Catholic": 24,
      "Canton_2": 115,
      "Commune_2": 116,
      "Church, Protestant_1": 24,
      "Church, Roman Catholic_1": 24,
      "Church, Christian Catholic_1": 24,
      "Canton_3": 302,
      "Commune_3": 0,
      "Church": 0,
      "Canton_4": 302,
      "Commune_4": 0,
      "Church_1": 0
    },
    {
      "Canton ID": 17,
      "Canton": "SG",
      "SFO Commune ID": 3315,
      "Commune": "Schänis",
      "Canton_1": 115,
      "Commune_1": 125,
      "Church, Protestant": 22.5,
      "Church, Roman Catholic": 25,
      "Church, Christian Catholic": 24,
      "Canton_2": 115,
      "Commune_2": 125,
      "Church, Protestant_1": 22.5,
      "Church, Roman Catholic_1": 25,
      "Church, Christian Catholic_1": 24,
      "Canton_3": 302,
      "Commune_3": 0,
      "Church": 0,
      "Canton_4": 302,
      "Commune_4": 0,
      "Church_1": 0
    },
    {
      "Canton ID": 17,
      "Canton": "SG",
      "SFO Commune ID": 3274,
      "Commune": "Sennwald",
      "Canton_1": 115,
      "Commune_1": 88,
      "Church, Protestant": 28,
      "Church, Roman Catholic": 18,
      "Church, Christian Catholic": 24,
      "Canton_2": 115,
      "Commune_2": 88,
      "Church, Protestant_1": 28,
      "Church, Roman Catholic_1": 18,
      "Church, Christian Catholic_1": 24,
      "Canton_3": 302,
      "Commune_3": 0,
      "Church": 0,
      "Canton_4": 302,
      "Commune_4": 0,
      "Church_1": 0
    },
    {
      "Canton ID": 17,
      "Canton": "SG",
      "SFO Commune ID": 3275,
      "Commune": "Sevelen",
      "Canton_1": 115,
      "Commune_1": 110,
      "Church, Protestant": 27,
      "Church, Roman Catholic": 20,
      "Church, Christian Catholic": 24,
      "Canton_2": 115,
      "Commune_2": 110,
      "Church, Protestant_1": 27,
      "Church, Roman Catholic_1": 20,
      "Church, Christian Catholic_1": 24,
      "Canton_3": 302,
      "Commune_3": 0,
      "Church": 0,
      "Canton_4": 302,
      "Commune_4": 0,
      "Church_1": 0
    },
    {
      "Canton ID": 17,
      "Canton": "SG",
      "SFO Commune ID": 3203,
      "Commune": "St. Gallen",
      "Canton_1": 115,
      "Commune_1": 141,
      "Church, Protestant": 26,
      "Church, Roman Catholic": 26,
      "Church, Christian Catholic": 24,
      "Canton_2": 115,
      "Commune_2": 141,
      "Church, Protestant_1": 26,
      "Church, Roman Catholic_1": 26,
      "Church, Christian Catholic_1": 24,
      "Canton_3": 302,
      "Commune_3": 0,
      "Church": 0,
      "Canton_4": 302,
      "Commune_4": 0,
      "Church_1": 0
    },
    {
      "Canton ID": 17,
      "Canton": "SG",
      "SFO Commune ID": 3236,
      "Commune": "St. Margrethen",
      "Canton_1": 115,
      "Commune_1": 114,
      "Church, Protestant": 28,
      "Church, Roman Catholic": 24,
      "Church, Christian Catholic": 24,
      "Canton_2": 115,
      "Commune_2": 114,
      "Church, Protestant_1": 28,
      "Church, Roman Catholic_1": 24,
      "Church, Christian Catholic_1": 24,
      "Canton_3": 302,
      "Commune_3": 0,
      "Church": 0,
      "Canton_4": 302,
      "Commune_4": 0,
      "Church_1": 0
    },
    {
      "Canton ID": 17,
      "Canton": "SG",
      "SFO Commune ID": 3217,
      "Commune": "Steinach",
      "Canton_1": 115,
      "Commune_1": 115,
      "Church, Protestant": 23,
      "Church, Roman Catholic": 27,
      "Church, Christian Catholic": 24,
      "Canton_2": 115,
      "Commune_2": 115,
      "Church, Protestant_1": 23,
      "Church, Roman Catholic_1": 27,
      "Church, Christian Catholic_1": 24,
      "Canton_3": 302,
      "Commune_3": 0,
      "Church": 0,
      "Canton_4": 302,
      "Commune_4": 0,
      "Church_1": 0
    },
    {
      "Canton ID": 17,
      "Canton": "SG",
      "SFO Commune ID": 3237,
      "Commune": "Thal",
      "Canton_1": 115,
      "Commune_1": 89,
      "Church, Protestant": 28,
      "Church, Roman Catholic": 27,
      "Church, Christian Catholic": 24,
      "Canton_2": 115,
      "Commune_2": 89,
      "Church, Protestant_1": 28,
      "Church, Roman Catholic_1": 27,
      "Church, Christian Catholic_1": 24,
      "Canton_3": 302,
      "Commune_3": 0,
      "Church": 0,
      "Canton_4": 302,
      "Commune_4": 0,
      "Church_1": 0
    },
    {
      "Canton ID": 17,
      "Canton": "SG",
      "SFO Commune ID": 3218,
      "Commune": "Tübach",
      "Canton_1": 115,
      "Commune_1": 82,
      "Church, Protestant": 23,
      "Church, Roman Catholic": 23,
      "Church, Christian Catholic": 24,
      "Canton_2": 115,
      "Commune_2": 82,
      "Church, Protestant_1": 23,
      "Church, Roman Catholic_1": 23,
      "Church, Christian Catholic_1": 24,
      "Canton_3": 302,
      "Commune_3": 0,
      "Church": 0,
      "Canton_4": 302,
      "Commune_4": 0,
      "Church_1": 0
    },
    {
      "Canton ID": 17,
      "Canton": "SG",
      "SFO Commune ID": 3219,
      "Commune": "Untereggen",
      "Canton_1": 115,
      "Commune_1": 119,
      "Church, Protestant": 23,
      "Church, Roman Catholic": 24,
      "Church, Christian Catholic": 24,
      "Canton_2": 115,
      "Commune_2": 119,
      "Church, Protestant_1": 23,
      "Church, Roman Catholic_1": 24,
      "Church, Christian Catholic_1": 24,
      "Canton_3": 302,
      "Commune_3": 0,
      "Church": 0,
      "Canton_4": 302,
      "Commune_4": 0,
      "Church_1": 0
    },
    {
      "Canton ID": 17,
      "Canton": "SG",
      "SFO Commune ID": 3339,
      "Commune": "Uznach",
      "Canton_1": 115,
      "Commune_1": 118,
      "Church, Protestant": 24,
      "Church, Roman Catholic": 24,
      "Church, Christian Catholic": 24,
      "Canton_2": 115,
      "Commune_2": 118,
      "Church, Protestant_1": 24,
      "Church, Roman Catholic_1": 24,
      "Church, Christian Catholic_1": 24,
      "Canton_3": 302,
      "Commune_3": 0,
      "Church": 0,
      "Canton_4": 302,
      "Commune_4": 0,
      "Church_1": 0
    },
    {
      "Canton ID": 17,
      "Canton": "SG",
      "SFO Commune ID": 3408,
      "Commune": "Uzwil",
      "Canton_1": 115,
      "Commune_1": 133,
      "Church, Protestant": 25,
      "Church, Roman Catholic": 23,
      "Church, Christian Catholic": 24,
      "Canton_2": 115,
      "Commune_2": 133,
      "Church, Protestant_1": 25,
      "Church, Roman Catholic_1": 23,
      "Church, Christian Catholic_1": 24,
      "Canton_3": 302,
      "Commune_3": 0,
      "Church": 0,
      "Canton_4": 302,
      "Commune_4": 0,
      "Church_1": 0
    },
    {
      "Canton ID": 17,
      "Canton": "SG",
      "SFO Commune ID": 3297,
      "Commune": "Vilters-Wangs",
      "Canton_1": 115,
      "Commune_1": 129,
      "Church, Protestant": 22,
      "Church, Roman Catholic": 24,
      "Church, Christian Catholic": 24,
      "Canton_2": 115,
      "Commune_2": 129,
      "Church, Protestant_1": 22,
      "Church, Roman Catholic_1": 24,
      "Church, Christian Catholic_1": 24,
      "Canton_3": 302,
      "Commune_3": 0,
      "Church": 0,
      "Canton_4": 302,
      "Commune_4": 0,
      "Church_1": 0
    },
    {
      "Canton ID": 17,
      "Canton": "SG",
      "SFO Commune ID": 3444,
      "Commune": "Waldkirch",
      "Canton_1": 115,
      "Commune_1": 122,
      "Church, Protestant": 28,
      "Church, Roman Catholic": 26,
      "Church, Christian Catholic": 24,
      "Canton_2": 115,
      "Commune_2": 122,
      "Church, Protestant_1": 28,
      "Church, Roman Catholic_1": 26,
      "Church, Christian Catholic_1": 24,
      "Canton_3": 302,
      "Commune_3": 0,
      "Church": 0,
      "Canton_4": 302,
      "Commune_4": 0,
      "Church_1": 0
    },
    {
      "Canton ID": 17,
      "Canton": "SG",
      "SFO Commune ID": 3298,
      "Commune": "Walenstadt",
      "Canton_1": 115,
      "Commune_1": 115,
      "Church, Protestant": 24,
      "Church, Roman Catholic": 24,
      "Church, Christian Catholic": 24,
      "Canton_2": 115,
      "Commune_2": 115,
      "Church, Protestant_1": 24,
      "Church, Roman Catholic_1": 24,
      "Church, Christian Catholic_1": 24,
      "Canton_3": 302,
      "Commune_3": 0,
      "Church": 0,
      "Canton_4": 302,
      "Commune_4": 0,
      "Church_1": 0
    },
    {
      "Canton ID": 17,
      "Canton": "SG",
      "SFO Commune ID": 3276,
      "Commune": "Wartau",
      "Canton_1": 115,
      "Commune_1": 160,
      "Church, Protestant": 28,
      "Church, Roman Catholic": 22,
      "Church, Christian Catholic": 24,
      "Canton_2": 115,
      "Commune_2": 160,
      "Church, Protestant_1": 28,
      "Church, Roman Catholic_1": 22,
      "Church, Christian Catholic_1": 24,
      "Canton_3": 302,
      "Commune_3": 0,
      "Church": 0,
      "Canton_4": 302,
      "Commune_4": 0,
      "Church_1": 0
    },
    {
      "Canton ID": 17,
      "Canton": "SG",
      "SFO Commune ID": 3379,
      "Commune": "Wattwil",
      "Canton_1": 115,
      "Commune_1": 132,
      "Church, Protestant": 28,
      "Church, Roman Catholic": 26,
      "Church, Christian Catholic": 24,
      "Canton_2": 115,
      "Commune_2": 132,
      "Church, Protestant_1": 28,
      "Church, Roman Catholic_1": 26,
      "Church, Christian Catholic_1": 24,
      "Canton_3": 302,
      "Commune_3": 0,
      "Church": 0,
      "Canton_4": 302,
      "Commune_4": 0,
      "Church_1": 0
    },
    {
      "Canton ID": 17,
      "Canton": "SG",
      "SFO Commune ID": 3316,
      "Commune": "Weesen",
      "Canton_1": 115,
      "Commune_1": 115,
      "Church, Protestant": 26,
      "Church, Roman Catholic": 26,
      "Church, Christian Catholic": 24,
      "Canton_2": 115,
      "Commune_2": 115,
      "Church, Protestant_1": 26,
      "Church, Roman Catholic_1": 26,
      "Church, Christian Catholic_1": 24,
      "Canton_3": 302,
      "Commune_3": 0,
      "Church": 0,
      "Canton_4": 302,
      "Commune_4": 0,
      "Church_1": 0
    },
    {
      "Canton ID": 17,
      "Canton": "SG",
      "SFO Commune ID": 3238,
      "Commune": "Widnau",
      "Canton_1": 115,
      "Commune_1": 76,
      "Church, Protestant": 24,
      "Church, Roman Catholic": 17,
      "Church, Christian Catholic": 24,
      "Canton_2": 115,
      "Commune_2": 76,
      "Church, Protestant_1": 24,
      "Church, Roman Catholic_1": 17,
      "Church, Christian Catholic_1": 24,
      "Canton_3": 302,
      "Commune_3": 0,
      "Church": 0,
      "Canton_4": 302,
      "Commune_4": 0,
      "Church_1": 0
    },
    {
      "Canton ID": 17,
      "Canton": "SG",
      "SFO Commune ID": 3427,
      "Commune": "Wil (SG)",
      "Canton_1": 115,
      "Commune_1": 118,
      "Church, Protestant": 23,
      "Church, Roman Catholic": 22,
      "Church, Christian Catholic": 24,
      "Canton_2": 115,
      "Commune_2": 118,
      "Church, Protestant_1": 23,
      "Church, Roman Catholic_1": 22,
      "Church, Christian Catholic_1": 24,
      "Canton_3": 302,
      "Commune_3": 0,
      "Church": 0,
      "Canton_4": 302,
      "Commune_4": 0,
      "Church_1": 0
    },
    {
      "Canton ID": 17,
      "Canton": "SG",
      "SFO Commune ID": 3359,
      "Commune": "Wildhaus-Alt St. Johann",
      "Canton_1": 115,
      "Commune_1": 128,
      "Church, Protestant": 28,
      "Church, Roman Catholic": 26,
      "Church, Christian Catholic": 24,
      "Canton_2": 115,
      "Commune_2": 128,
      "Church, Protestant_1": 28,
      "Church, Roman Catholic_1": 26,
      "Church, Christian Catholic_1": 24,
      "Canton_3": 302,
      "Commune_3": 0,
      "Church": 0,
      "Canton_4": 302,
      "Commune_4": 0,
      "Church_1": 0
    },
    {
      "Canton ID": 17,
      "Canton": "SG",
      "SFO Commune ID": 3204,
      "Commune": "Wittenbach",
      "Canton_1": 115,
      "Commune_1": 133,
      "Church, Protestant": 25,
      "Church, Roman Catholic": 24,
      "Church, Christian Catholic": 24,
      "Canton_2": 115,
      "Commune_2": 133,
      "Church, Protestant_1": 25,
      "Church, Roman Catholic_1": 24,
      "Church, Christian Catholic_1": 24,
      "Canton_3": 302,
      "Commune_3": 0,
      "Church": 0,
      "Canton_4": 302,
      "Commune_4": 0,
      "Church_1": 0
    },
    {
      "Canton ID": 17,
      "Canton": "SG",
      "SFO Commune ID": 3426,
      "Commune": "Zuzwil (SG)",
      "Canton_1": 115,
      "Commune_1": 82,
      "Church, Protestant": 23,
      "Church, Roman Catholic": 21,
      "Church, Christian Catholic": 24,
      "Canton_2": 115,
      "Commune_2": 82,
      "Church, Protestant_1": 23,
      "Church, Roman Catholic_1": 21,
      "Church, Christian Catholic_1": 24,
      "Canton_3": 302,
      "Commune_3": 0,
      "Church": 0,
      "Canton_4": 302,
      "Commune_4": 0,
      "Church_1": 0
    }
  ],
  "2019": [
    [
      {
        "Canton ID": 17,
        "Canton": "SG",
        "SFO Commune ID": 3251,
        "Commune": "Altstätten",
        "Canton__1": 115,
        "Commune__1": 129,
        "Church, Protestant": 28,
        "Church, Roman Catholic": 20,
        "Church, Christian Catholic": 24,
        "Canton__2": 115,
        "Commune__2": 129,
        "Church, Protestant__1": 28,
        "Church, Roman Catholic__1": 20,
        "Church, Christian Catholic__1": 24,
        "Canton__3": 0,
        "Commune__3": 0,
        "Church": 0,
        "Canton__4": 0,
        "Commune__4": 0,
        "Church__1": 0
      },
      {
        "Canton ID": 17,
        "Canton": "SG",
        "SFO Commune ID": 3311,
        "Commune": "Amden",
        "Canton__1": 115,
        "Commune__1": 120,
        "Church, Protestant": 27,
        "Church, Roman Catholic": 25,
        "Church, Christian Catholic": 24,
        "Canton__2": 115,
        "Commune__2": 120,
        "Church, Protestant__1": 27,
        "Church, Roman Catholic__1": 25,
        "Church, Christian Catholic__1": 24,
        "Canton__3": 0,
        "Commune__3": 0,
        "Church": 0,
        "Canton__4": 0,
        "Commune__4": 0,
        "Church__1": 0
      },
      {
        "Canton ID": 17,
        "Canton": "SG",
        "SFO Commune ID": 3441,
        "Commune": "Andwil (SG)",
        "Canton__1": 115,
        "Commune__1": 118,
        "Church, Protestant": 23,
        "Church, Roman Catholic": 28,
        "Church, Christian Catholic": 24,
        "Canton__2": 115,
        "Commune__2": 118,
        "Church, Protestant__1": 23,
        "Church, Roman Catholic__1": 28,
        "Church, Christian Catholic__1": 24,
        "Canton__3": 0,
        "Commune__3": 0,
        "Church": 0,
        "Canton__4": 0,
        "Commune__4": 0,
        "Church__1": 0
      },
      {
        "Canton ID": 17,
        "Canton": "SG",
        "SFO Commune ID": 3231,
        "Commune": "Au (SG)",
        "Canton__1": 115,
        "Commune__1": 90,
        "Church, Protestant": 25,
        "Church, Roman Catholic": 21,
        "Church, Christian Catholic": 24,
        "Canton__2": 115,
        "Commune__2": 90,
        "Church, Protestant__1": 25,
        "Church, Roman Catholic__1": 21,
        "Church, Christian Catholic__1": 24,
        "Canton__3": 0,
        "Commune__3": 0,
        "Church": 0,
        "Canton__4": 0,
        "Commune__4": 0,
        "Church__1": 0
      },
      {
        "Canton ID": 17,
        "Canton": "SG",
        "SFO Commune ID": 3291,
        "Commune": "Bad Ragaz",
        "Canton__1": 115,
        "Commune__1": 92,
        "Church, Protestant": 28,
        "Church, Roman Catholic": 17,
        "Church, Christian Catholic": 24,
        "Canton__2": 115,
        "Commune__2": 92,
        "Church, Protestant__1": 28,
        "Church, Roman Catholic__1": 17,
        "Church, Christian Catholic__1": 24,
        "Canton__3": 0,
        "Commune__3": 0,
        "Church": 0,
        "Canton__4": 0,
        "Commune__4": 0,
        "Church__1": 0
      },
      {
        "Canton ID": 17,
        "Canton": "SG",
        "SFO Commune ID": 3232,
        "Commune": "Balgach",
        "Canton__1": 115,
        "Commune__1": 77,
        "Church, Protestant": 25,
        "Church, Roman Catholic": 21,
        "Church, Christian Catholic": 24,
        "Canton__2": 115,
        "Commune__2": 77,
        "Church, Protestant__1": 25,
        "Church, Roman Catholic__1": 21,
        "Church, Christian Catholic__1": 24,
        "Canton__3": 0,
        "Commune__3": 0,
        "Church": 0,
        "Canton__4": 0,
        "Commune__4": 0,
        "Church__1": 0
      },
      {
        "Canton ID": 17,
        "Canton": "SG",
        "SFO Commune ID": 3312,
        "Commune": "Benken (SG)",
        "Canton__1": 115,
        "Commune__1": 135,
        "Church, Protestant": 24,
        "Church, Roman Catholic": 24,
        "Church, Christian Catholic": 24,
        "Canton__2": 115,
        "Commune__2": 135,
        "Church, Protestant__1": 24,
        "Church, Roman Catholic__1": 24,
        "Church, Christian Catholic__1": 24,
        "Canton__3": 0,
        "Commune__3": 0,
        "Church": 0,
        "Canton__4": 0,
        "Commune__4": 0,
        "Church__1": 0
      },
      {
        "Canton ID": 17,
        "Canton": "SG",
        "SFO Commune ID": 3211,
        "Commune": "Berg (SG)",
        "Canton__1": 115,
        "Commune__1": 136,
        "Church, Protestant": 18,
        "Church, Roman Catholic": 24,
        "Church, Christian Catholic": 24,
        "Canton__2": 115,
        "Commune__2": 136,
        "Church, Protestant__1": 18,
        "Church, Roman Catholic__1": 24,
        "Church, Christian Catholic__1": 24,
        "Canton__3": 0,
        "Commune__3": 0,
        "Church": 0,
        "Canton__4": 0,
        "Commune__4": 0,
        "Church__1": 0
      },
      {
        "Canton ID": 17,
        "Canton": "SG",
        "SFO Commune ID": 3233,
        "Commune": "Berneck",
        "Canton__1": 115,
        "Commune__1": 97,
        "Church, Protestant": 25,
        "Church, Roman Catholic": 21,
        "Church, Christian Catholic": 24,
        "Canton__2": 115,
        "Commune__2": 97,
        "Church, Protestant__1": 25,
        "Church, Roman Catholic__1": 21,
        "Church, Christian Catholic__1": 24,
        "Canton__3": 0,
        "Commune__3": 0,
        "Church": 0,
        "Canton__4": 0,
        "Commune__4": 0,
        "Church__1": 0
      },
      {
        "Canton ID": 17,
        "Canton": "SG",
        "SFO Commune ID": 3271,
        "Commune": "Buchs (SG)",
        "Canton__1": 115,
        "Commune__1": 118,
        "Church, Protestant": 27,
        "Church, Roman Catholic": 18,
        "Church, Christian Catholic": 24,
        "Canton__2": 115,
        "Commune__2": 118,
        "Church, Protestant__1": 27,
        "Church, Roman Catholic__1": 18,
        "Church, Christian Catholic__1": 24,
        "Canton__3": 0,
        "Commune__3": 0,
        "Church": 0,
        "Canton__4": 0,
        "Commune__4": 0,
        "Church__1": 0
      },
      {
        "Canton ID": 17,
        "Canton": "SG",
        "SFO Commune ID": 3395,
        "Commune": "Bütschwil-Ganterschwil",
        "Canton__1": 115,
        "Commune__1": 134,
        "Church, Protestant": 28,
        "Church, Roman Catholic": 25,
        "Church, Christian Catholic": 24,
        "Canton__2": 115,
        "Commune__2": 134,
        "Church, Protestant__1": 28,
        "Church, Roman Catholic__1": 25,
        "Church, Christian Catholic__1": 24,
        "Canton__3": 0,
        "Commune__3": 0,
        "Church": 0,
        "Canton__4": 0,
        "Commune__4": 0,
        "Church__1": 0
      },
      {
        "Canton ID": 17,
        "Canton": "SG",
        "SFO Commune ID": 3401,
        "Commune": "Degersheim",
        "Canton__1": 115,
        "Commune__1": 159,
        "Church, Protestant": 28,
        "Church, Roman Catholic": 26,
        "Church, Christian Catholic": 24,
        "Canton__2": 115,
        "Commune__2": 159,
        "Church, Protestant__1": 28,
        "Church, Roman Catholic__1": 26,
        "Church, Christian Catholic__1": 24,
        "Canton__3": 0,
        "Commune__3": 0,
        "Church": 0,
        "Canton__4": 0,
        "Commune__4": 0,
        "Church__1": 0
      },
      {
        "Canton ID": 17,
        "Canton": "SG",
        "SFO Commune ID": 3234,
        "Commune": "Diepoldsau",
        "Canton__1": 115,
        "Commune__1": 89,
        "Church, Protestant": 24,
        "Church, Roman Catholic": 21,
        "Church, Christian Catholic": 24,
        "Canton__2": 115,
        "Commune__2": 89,
        "Church, Protestant__1": 24,
        "Church, Roman Catholic__1": 21,
        "Church, Christian Catholic__1": 24,
        "Canton__3": 0,
        "Commune__3": 0,
        "Church": 0,
        "Canton__4": 0,
        "Commune__4": 0,
        "Church__1": 0
      },
      {
        "Canton ID": 17,
        "Canton": "SG",
        "SFO Commune ID": 3352,
        "Commune": "Ebnat-Kappel",
        "Canton__1": 115,
        "Commune__1": 145,
        "Church, Protestant": 28,
        "Church, Roman Catholic": 27,
        "Church, Christian Catholic": 24,
        "Canton__2": 115,
        "Commune__2": 145,
        "Church, Protestant__1": 28,
        "Church, Roman Catholic__1": 27,
        "Church, Christian Catholic__1": 24,
        "Canton__3": 0,
        "Commune__3": 0,
        "Church": 0,
        "Canton__4": 0,
        "Commune__4": 0,
        "Church__1": 0
      },
      {
        "Canton ID": 17,
        "Canton": "SG",
        "SFO Commune ID": 3212,
        "Commune": "Eggersriet",
        "Canton__1": 115,
        "Commune__1": 128,
        "Church, Protestant": 24,
        "Church, Roman Catholic": 26,
        "Church, Christian Catholic": 24,
        "Canton__2": 115,
        "Commune__2": 128,
        "Church, Protestant__1": 24,
        "Church, Roman Catholic__1": 26,
        "Church, Christian Catholic__1": 24,
        "Canton__3": 0,
        "Commune__3": 0,
        "Church": 0,
        "Canton__4": 0,
        "Commune__4": 0,
        "Church__1": 0
      },
      {
        "Canton ID": 17,
        "Canton": "SG",
        "SFO Commune ID": 3252,
        "Commune": "Eichberg",
        "Canton__1": 115,
        "Commune__1": 128,
        "Church, Protestant": 28,
        "Church, Roman Catholic": 20,
        "Church, Christian Catholic": 24,
        "Canton__2": 115,
        "Commune__2": 128,
        "Church, Protestant__1": 28,
        "Church, Roman Catholic__1": 20,
        "Church, Christian Catholic__1": 24,
        "Canton__3": 0,
        "Commune__3": 0,
        "Church": 0,
        "Canton__4": 0,
        "Commune__4": 0,
        "Church__1": 0
      },
      {
        "Canton ID": 17,
        "Canton": "SG",
        "SFO Commune ID": 3342,
        "Commune": "Eschenbach (SG)",
        "Canton__1": 115,
        "Commune__1": 121,
        "Church, Protestant": 24,
        "Church, Roman Catholic": 24,
        "Church, Christian Catholic": 24,
        "Canton__2": 115,
        "Commune__2": 121,
        "Church, Protestant__1": 24,
        "Church, Roman Catholic__1": 24,
        "Church, Christian Catholic__1": 24,
        "Canton__3": 0,
        "Commune__3": 0,
        "Church": 0,
        "Canton__4": 0,
        "Commune__4": 0,
        "Church__1": 0
      },
      {
        "Canton ID": 17,
        "Canton": "SG",
        "SFO Commune ID": 3402,
        "Commune": "Flawil",
        "Canton__1": 115,
        "Commune__1": 138,
        "Church, Protestant": 27,
        "Church, Roman Catholic": 25,
        "Church, Christian Catholic": 24,
        "Canton__2": 115,
        "Commune__2": 138,
        "Church, Protestant__1": 27,
        "Church, Roman Catholic__1": 25,
        "Church, Christian Catholic__1": 24,
        "Canton__3": 0,
        "Commune__3": 0,
        "Church": 0,
        "Canton__4": 0,
        "Commune__4": 0,
        "Church__1": 0
      },
      {
        "Canton ID": 17,
        "Canton": "SG",
        "SFO Commune ID": 3292,
        "Commune": "Flums",
        "Canton__1": 115,
        "Commune__1": 135,
        "Church, Protestant": 24,
        "Church, Roman Catholic": 26,
        "Church, Christian Catholic": 24,
        "Canton__2": 115,
        "Commune__2": 135,
        "Church, Protestant__1": 24,
        "Church, Roman Catholic__1": 26,
        "Church, Christian Catholic__1": 24,
        "Canton__3": 0,
        "Commune__3": 0,
        "Church": 0,
        "Canton__4": 0,
        "Commune__4": 0,
        "Church__1": 0
      },
      {
        "Canton ID": 17,
        "Canton": "SG",
        "SFO Commune ID": 3442,
        "Commune": "Gaiserwald",
        "Canton__1": 115,
        "Commune__1": 107,
        "Church, Protestant": 21,
        "Church, Roman Catholic": 21,
        "Church, Christian Catholic": 24,
        "Canton__2": 115,
        "Commune__2": 107,
        "Church, Protestant__1": 21,
        "Church, Roman Catholic__1": 21,
        "Church, Christian Catholic__1": 24,
        "Canton__3": 0,
        "Commune__3": 0,
        "Church": 0,
        "Canton__4": 0,
        "Commune__4": 0,
        "Church__1": 0
      },
      {
        "Canton ID": 17,
        "Canton": "SG",
        "SFO Commune ID": 3272,
        "Commune": "Gams",
        "Canton__1": 115,
        "Commune__1": 129,
        "Church, Protestant": 27,
        "Church, Roman Catholic": 24,
        "Church, Christian Catholic": 24,
        "Canton__2": 115,
        "Commune__2": 129,
        "Church, Protestant__1": 27,
        "Church, Roman Catholic__1": 24,
        "Church, Christian Catholic__1": 24,
        "Canton__3": 0,
        "Commune__3": 0,
        "Church": 0,
        "Canton__4": 0,
        "Commune__4": 0,
        "Church__1": 0
      },
      {
        "Canton ID": 17,
        "Canton": "SG",
        "SFO Commune ID": 3213,
        "Commune": "Goldach",
        "Canton__1": 115,
        "Commune__1": 101,
        "Church, Protestant": 23,
        "Church, Roman Catholic": 24,
        "Church, Christian Catholic": 24,
        "Canton__2": 115,
        "Commune__2": 101,
        "Church, Protestant__1": 23,
        "Church, Roman Catholic__1": 24,
        "Church, Christian Catholic__1": 24,
        "Canton__3": 0,
        "Commune__3": 0,
        "Church": 0,
        "Canton__4": 0,
        "Commune__4": 0,
        "Church__1": 0
      },
      {
        "Canton ID": 17,
        "Canton": "SG",
        "SFO Commune ID": 3341,
        "Commune": "Gommiswald",
        "Canton__1": 115,
        "Commune__1": 116,
        "Church, Protestant": 24,
        "Church, Roman Catholic": 28,
        "Church, Christian Catholic": 24,
        "Canton__2": 115,
        "Commune__2": 116,
        "Church, Protestant__1": 24,
        "Church, Roman Catholic__1": 28,
        "Church, Christian Catholic__1": 24,
        "Canton__3": 0,
        "Commune__3": 0,
        "Church": 0,
        "Canton__4": 0,
        "Commune__4": 0,
        "Church__1": 0
      },
      {
        "Canton ID": 17,
        "Canton": "SG",
        "SFO Commune ID": 3443,
        "Commune": "Gossau (SG)",
        "Canton__1": 115,
        "Commune__1": 121,
        "Church, Protestant": 23,
        "Church, Roman Catholic": 23,
        "Church, Christian Catholic": 24,
        "Canton__2": 115,
        "Commune__2": 121,
        "Church, Protestant__1": 23,
        "Church, Roman Catholic__1": 23,
        "Church, Christian Catholic__1": 24,
        "Canton__3": 0,
        "Commune__3": 0,
        "Church": 0,
        "Canton__4": 0,
        "Commune__4": 0,
        "Church__1": 0
      },
      {
        "Canton ID": 17,
        "Canton": "SG",
        "SFO Commune ID": 3273,
        "Commune": "Grabs",
        "Canton__1": 115,
        "Commune__1": 120,
        "Church, Protestant": 27,
        "Church, Roman Catholic": 18,
        "Church, Christian Catholic": 24,
        "Canton__2": 115,
        "Commune__2": 120,
        "Church, Protestant__1": 27,
        "Church, Roman Catholic__1": 18,
        "Church, Christian Catholic__1": 24,
        "Canton__3": 0,
        "Commune__3": 0,
        "Church": 0,
        "Canton__4": 0,
        "Commune__4": 0,
        "Church__1": 0
      },
      {
        "Canton ID": 17,
        "Canton": "SG",
        "SFO Commune ID": 3372,
        "Commune": "Hemberg",
        "Canton__1": 115,
        "Commune__1": 138,
        "Church, Protestant": 28,
        "Church, Roman Catholic": 26,
        "Church, Christian Catholic": 24,
        "Canton__2": 115,
        "Commune__2": 138,
        "Church, Protestant__1": 28,
        "Church, Roman Catholic__1": 26,
        "Church, Christian Catholic__1": 24,
        "Canton__3": 0,
        "Commune__3": 0,
        "Church": 0,
        "Canton__4": 0,
        "Commune__4": 0,
        "Church__1": 0
      },
      {
        "Canton ID": 17,
        "Canton": "SG",
        "SFO Commune ID": 3201,
        "Commune": "Häggenschwil",
        "Canton__1": 115,
        "Commune__1": 119,
        "Church, Protestant": 18,
        "Church, Roman Catholic": 24,
        "Church, Christian Catholic": 24,
        "Canton__2": 115,
        "Commune__2": 119,
        "Church, Protestant__1": 18,
        "Church, Roman Catholic__1": 24,
        "Church, Christian Catholic__1": 24,
        "Canton__3": 0,
        "Commune__3": 0,
        "Church": 0,
        "Canton__4": 0,
        "Commune__4": 0,
        "Church__1": 0
      },
      {
        "Canton ID": 17,
        "Canton": "SG",
        "SFO Commune ID": 3405,
        "Commune": "Jonschwil",
        "Canton__1": 115,
        "Commune__1": 135,
        "Church, Protestant": 25,
        "Church, Roman Catholic": 26,
        "Church, Christian Catholic": 24,
        "Canton__2": 115,
        "Commune__2": 135,
        "Church, Protestant__1": 25,
        "Church, Roman Catholic__1": 26,
        "Church, Christian Catholic__1": 24,
        "Canton__3": 0,
        "Commune__3": 0,
        "Church": 0,
        "Canton__4": 0,
        "Commune__4": 0,
        "Church__1": 0
      },
      {
        "Canton ID": 17,
        "Canton": "SG",
        "SFO Commune ID": 3313,
        "Commune": "Kaltbrunn",
        "Canton__1": 115,
        "Commune__1": 108,
        "Church, Protestant": 24,
        "Church, Roman Catholic": 21,
        "Church, Christian Catholic": 24,
        "Canton__2": 115,
        "Commune__2": 108,
        "Church, Protestant__1": 24,
        "Church, Roman Catholic__1": 21,
        "Church, Christian Catholic__1": 24,
        "Canton__3": 0,
        "Commune__3": 0,
        "Church": 0,
        "Canton__4": 0,
        "Commune__4": 0,
        "Church__1": 0
      },
      {
        "Canton ID": 17,
        "Canton": "SG",
        "SFO Commune ID": 3392,
        "Commune": "Kirchberg (SG)",
        "Canton__1": 115,
        "Commune__1": 138,
        "Church, Protestant": 26,
        "Church, Roman Catholic": 24,
        "Church, Christian Catholic": 24,
        "Canton__2": 115,
        "Commune__2": 138,
        "Church, Protestant__1": 26,
        "Church, Roman Catholic__1": 24,
        "Church, Christian Catholic__1": 24,
        "Canton__3": 0,
        "Commune__3": 0,
        "Church": 0,
        "Canton__4": 0,
        "Commune__4": 0,
        "Church__1": 0
      },
      {
        "Canton ID": 17,
        "Canton": "SG",
        "SFO Commune ID": 3374,
        "Commune": "Lichtensteig",
        "Canton__1": 115,
        "Commune__1": 140,
        "Church, Protestant": 28,
        "Church, Roman Catholic": 27,
        "Church, Christian Catholic": 24,
        "Canton__2": 115,
        "Commune__2": 140,
        "Church, Protestant__1": 28,
        "Church, Roman Catholic__1": 27,
        "Church, Christian Catholic__1": 24,
        "Canton__3": 0,
        "Commune__3": 0,
        "Church": 0,
        "Canton__4": 0,
        "Commune__4": 0,
        "Church__1": 0
      },
      {
        "Canton ID": 17,
        "Canton": "SG",
        "SFO Commune ID": 3393,
        "Commune": "Lütisburg",
        "Canton__1": 115,
        "Commune__1": 135,
        "Church, Protestant": 28,
        "Church, Roman Catholic": 26,
        "Church, Christian Catholic": 24,
        "Canton__2": 115,
        "Commune__2": 135,
        "Church, Protestant__1": 28,
        "Church, Roman Catholic__1": 26,
        "Church, Christian Catholic__1": 24,
        "Canton__3": 0,
        "Commune__3": 0,
        "Church": 0,
        "Canton__4": 0,
        "Commune__4": 0,
        "Church__1": 0
      },
      {
        "Canton ID": 17,
        "Canton": "SG",
        "SFO Commune ID": 3253,
        "Commune": "Marbach (SG)",
        "Canton__1": 115,
        "Commune__1": 120,
        "Church, Protestant": 28,
        "Church, Roman Catholic": 26,
        "Church, Christian Catholic": 24,
        "Canton__2": 115,
        "Commune__2": 120,
        "Church, Protestant__1": 28,
        "Church, Roman Catholic__1": 26,
        "Church, Christian Catholic__1": 24,
        "Canton__3": 0,
        "Commune__3": 0,
        "Church": 0,
        "Canton__4": 0,
        "Commune__4": 0,
        "Church__1": 0
      },
      {
        "Canton ID": 17,
        "Canton": "SG",
        "SFO Commune ID": 3293,
        "Commune": "Mels",
        "Canton__1": 115,
        "Commune__1": 133,
        "Church, Protestant": 24,
        "Church, Roman Catholic": 22,
        "Church, Christian Catholic": 24,
        "Canton__2": 115,
        "Commune__2": 133,
        "Church, Protestant__1": 24,
        "Church, Roman Catholic__1": 22,
        "Church, Christian Catholic__1": 24,
        "Canton__3": 0,
        "Commune__3": 0,
        "Church": 0,
        "Canton__4": 0,
        "Commune__4": 0,
        "Church__1": 0
      },
      {
        "Canton ID": 17,
        "Canton": "SG",
        "SFO Commune ID": 3394,
        "Commune": "Mosnang",
        "Canton__1": 115,
        "Commune__1": 137,
        "Church, Protestant": 28,
        "Church, Roman Catholic": 26,
        "Church, Christian Catholic": 24,
        "Canton__2": 115,
        "Commune__2": 137,
        "Church, Protestant__1": 28,
        "Church, Roman Catholic__1": 26,
        "Church, Christian Catholic__1": 24,
        "Canton__3": 0,
        "Commune__3": 0,
        "Church": 0,
        "Canton__4": 0,
        "Commune__4": 0,
        "Church__1": 0
      },
      {
        "Canton ID": 17,
        "Canton": "SG",
        "SFO Commune ID": 3202,
        "Commune": "Muolen",
        "Canton__1": 115,
        "Commune__1": 132,
        "Church, Protestant": 20,
        "Church, Roman Catholic": 26,
        "Church, Christian Catholic": 24,
        "Canton__2": 115,
        "Commune__2": 132,
        "Church, Protestant__1": 20,
        "Church, Roman Catholic__1": 26,
        "Church, Christian Catholic__1": 24,
        "Canton__3": 0,
        "Commune__3": 0,
        "Church": 0,
        "Canton__4": 0,
        "Commune__4": 0,
        "Church__1": 0
      },
      {
        "Canton ID": 17,
        "Canton": "SG",
        "SFO Commune ID": 3214,
        "Commune": "Mörschwil",
        "Canton__1": 115,
        "Commune__1": 75,
        "Church, Protestant": 23,
        "Church, Roman Catholic": 16,
        "Church, Christian Catholic": 24,
        "Canton__2": 115,
        "Commune__2": 75,
        "Church, Protestant__1": 23,
        "Church, Roman Catholic__1": 16,
        "Church, Christian Catholic__1": 24,
        "Canton__3": 0,
        "Commune__3": 0,
        "Church": 0,
        "Canton__4": 0,
        "Commune__4": 0,
        "Church__1": 0
      },
      {
        "Canton ID": 17,
        "Canton": "SG",
        "SFO Commune ID": 3378,
        "Commune": "Neckertal",
        "Canton__1": 115,
        "Commune__1": 132,
        "Church, Protestant": 28,
        "Church, Roman Catholic": 24,
        "Church, Christian Catholic": 24,
        "Canton__2": 115,
        "Commune__2": 132,
        "Church, Protestant__1": 28,
        "Church, Roman Catholic__1": 24,
        "Church, Christian Catholic__1": 24,
        "Canton__3": 0,
        "Commune__3": 0,
        "Church": 0,
        "Canton__4": 0,
        "Commune__4": 0,
        "Church__1": 0
      },
      {
        "Canton ID": 17,
        "Canton": "SG",
        "SFO Commune ID": 3360,
        "Commune": "Nesslau",
        "Canton__1": 115,
        "Commune__1": 125,
        "Church, Protestant": 28,
        "Church, Roman Catholic": 26,
        "Church, Christian Catholic": 24,
        "Canton__2": 115,
        "Commune__2": 125,
        "Church, Protestant__1": 28,
        "Church, Roman Catholic__1": 26,
        "Church, Christian Catholic__1": 24,
        "Canton__3": 0,
        "Commune__3": 0,
        "Church": 0,
        "Canton__4": 0,
        "Commune__4": 0,
        "Church__1": 0
      },
      {
        "Canton ID": 17,
        "Canton": "SG",
        "SFO Commune ID": 3422,
        "Commune": "Niederbüren",
        "Canton__1": 115,
        "Commune__1": 129,
        "Church, Protestant": 28,
        "Church, Roman Catholic": 25,
        "Church, Christian Catholic": 24,
        "Canton__2": 115,
        "Commune__2": 129,
        "Church, Protestant__1": 28,
        "Church, Roman Catholic__1": 25,
        "Church, Christian Catholic__1": 24,
        "Canton__3": 0,
        "Commune__3": 0,
        "Church": 0,
        "Canton__4": 0,
        "Commune__4": 0,
        "Church__1": 0
      },
      {
        "Canton ID": 17,
        "Canton": "SG",
        "SFO Commune ID": 3423,
        "Commune": "Niederhelfenschwil",
        "Canton__1": 115,
        "Commune__1": 114,
        "Church, Protestant": 32,
        "Church, Roman Catholic": 24,
        "Church, Christian Catholic": 24,
        "Canton__2": 115,
        "Commune__2": 114,
        "Church, Protestant__1": 32,
        "Church, Roman Catholic__1": 24,
        "Church, Christian Catholic__1": 24,
        "Canton__3": 0,
        "Commune__3": 0,
        "Church": 0,
        "Canton__4": 0,
        "Commune__4": 0,
        "Church__1": 0
      },
      {
        "Canton ID": 17,
        "Canton": "SG",
        "SFO Commune ID": 3424,
        "Commune": "Oberbüren",
        "Canton__1": 115,
        "Commune__1": 105,
        "Church, Protestant": 25,
        "Church, Roman Catholic": 29,
        "Church, Christian Catholic": 24,
        "Canton__2": 115,
        "Commune__2": 105,
        "Church, Protestant__1": 25,
        "Church, Roman Catholic__1": 29,
        "Church, Christian Catholic__1": 24,
        "Canton__3": 0,
        "Commune__3": 0,
        "Church": 0,
        "Canton__4": 0,
        "Commune__4": 0,
        "Church__1": 0
      },
      {
        "Canton ID": 17,
        "Canton": "SG",
        "SFO Commune ID": 3375,
        "Commune": "Oberhelfenschwil",
        "Canton__1": 115,
        "Commune__1": 139,
        "Church, Protestant": 28,
        "Church, Roman Catholic": 25,
        "Church, Christian Catholic": 24,
        "Canton__2": 115,
        "Commune__2": 139,
        "Church, Protestant__1": 28,
        "Church, Roman Catholic__1": 25,
        "Church, Christian Catholic__1": 24,
        "Canton__3": 0,
        "Commune__3": 0,
        "Church": 0,
        "Canton__4": 0,
        "Commune__4": 0,
        "Church__1": 0
      },
      {
        "Canton ID": 17,
        "Canton": "SG",
        "SFO Commune ID": 3254,
        "Commune": "Oberriet (SG)",
        "Canton__1": 115,
        "Commune__1": 112,
        "Church, Protestant": 28,
        "Church, Roman Catholic": 25,
        "Church, Christian Catholic": 24,
        "Canton__2": 115,
        "Commune__2": 112,
        "Church, Protestant__1": 28,
        "Church, Roman Catholic__1": 25,
        "Church, Christian Catholic__1": 24,
        "Canton__3": 0,
        "Commune__3": 0,
        "Church": 0,
        "Canton__4": 0,
        "Commune__4": 0,
        "Church__1": 0
      },
      {
        "Canton ID": 17,
        "Canton": "SG",
        "SFO Commune ID": 3407,
        "Commune": "Oberuzwil",
        "Canton__1": 115,
        "Commune__1": 129,
        "Church, Protestant": 25,
        "Church, Roman Catholic": 24,
        "Church, Christian Catholic": 24,
        "Canton__2": 115,
        "Commune__2": 129,
        "Church, Protestant__1": 25,
        "Church, Roman Catholic__1": 24,
        "Church, Christian Catholic__1": 24,
        "Canton__3": 0,
        "Commune__3": 0,
        "Church": 0,
        "Canton__4": 0,
        "Commune__4": 0,
        "Church__1": 0
      },
      {
        "Canton ID": 17,
        "Canton": "SG",
        "SFO Commune ID": 3294,
        "Commune": "Pfäfers",
        "Canton__1": 115,
        "Commune__1": 147,
        "Church, Protestant": 28,
        "Church, Roman Catholic": 25,
        "Church, Christian Catholic": 24,
        "Canton__2": 115,
        "Commune__2": 147,
        "Church, Protestant__1": 28,
        "Church, Roman Catholic__1": 25,
        "Church, Christian Catholic__1": 24,
        "Canton__3": 0,
        "Commune__3": 0,
        "Church": 0,
        "Canton__4": 0,
        "Commune__4": 0,
        "Church__1": 0
      },
      {
        "Canton ID": 17,
        "Canton": "SG",
        "SFO Commune ID": 3295,
        "Commune": "Quarten",
        "Canton__1": 115,
        "Commune__1": 118,
        "Church, Protestant": 24,
        "Church, Roman Catholic": 25,
        "Church, Christian Catholic": 24,
        "Canton__2": 115,
        "Commune__2": 118,
        "Church, Protestant__1": 24,
        "Church, Roman Catholic__1": 25,
        "Church, Christian Catholic__1": 24,
        "Canton__3": 0,
        "Commune__3": 0,
        "Church": 0,
        "Canton__4": 0,
        "Commune__4": 0,
        "Church__1": 0
      },
      {
        "Canton ID": 17,
        "Canton": "SG",
        "SFO Commune ID": 3340,
        "Commune": "Rapperswil-Jona",
        "Canton__1": 115,
        "Commune__1": 76,
        "Church, Protestant": 20,
        "Church, Roman Catholic": 19,
        "Church, Christian Catholic": 24,
        "Canton__2": 115,
        "Commune__2": 76,
        "Church, Protestant__1": 20,
        "Church, Roman Catholic__1": 19,
        "Church, Christian Catholic__1": 24,
        "Canton__3": 0,
        "Commune__3": 0,
        "Church": 0,
        "Canton__4": 0,
        "Commune__4": 0,
        "Church__1": 0
      },
      {
        "Canton ID": 17,
        "Canton": "SG",
        "SFO Commune ID": 3255,
        "Commune": "Rebstein",
        "Canton__1": 115,
        "Commune__1": 114,
        "Church, Protestant": 28,
        "Church, Roman Catholic": 29,
        "Church, Christian Catholic": 24,
        "Canton__2": 115,
        "Commune__2": 114,
        "Church, Protestant__1": 28,
        "Church, Roman Catholic__1": 29,
        "Church, Christian Catholic__1": 24,
        "Canton__3": 0,
        "Commune__3": 0,
        "Church": 0,
        "Canton__4": 0,
        "Commune__4": 0,
        "Church__1": 0
      },
      {
        "Canton ID": 17,
        "Canton": "SG",
        "SFO Commune ID": 3235,
        "Commune": "Rheineck",
        "Canton__1": 115,
        "Commune__1": 124,
        "Church, Protestant": 28,
        "Church, Roman Catholic": 24,
        "Church, Christian Catholic": 24,
        "Canton__2": 115,
        "Commune__2": 124,
        "Church, Protestant__1": 28,
        "Church, Roman Catholic__1": 24,
        "Church, Christian Catholic__1": 24,
        "Canton__3": 0,
        "Commune__3": 0,
        "Church": 0,
        "Canton__4": 0,
        "Commune__4": 0,
        "Church__1": 0
      },
      {
        "Canton ID": 17,
        "Canton": "SG",
        "SFO Commune ID": 3215,
        "Commune": "Rorschach",
        "Canton__1": 115,
        "Commune__1": 139,
        "Church, Protestant": 28,
        "Church, Roman Catholic": 24,
        "Church, Christian Catholic": 24,
        "Canton__2": 115,
        "Commune__2": 139,
        "Church, Protestant__1": 28,
        "Church, Roman Catholic__1": 24,
        "Church, Christian Catholic__1": 24,
        "Canton__3": 0,
        "Commune__3": 0,
        "Church": 0,
        "Canton__4": 0,
        "Commune__4": 0,
        "Church__1": 0
      },
      {
        "Canton ID": 17,
        "Canton": "SG",
        "SFO Commune ID": 3216,
        "Commune": "Rorschacherberg",
        "Canton__1": 115,
        "Commune__1": 99,
        "Church, Protestant": 28,
        "Church, Roman Catholic": 24,
        "Church, Christian Catholic": 24,
        "Canton__2": 115,
        "Commune__2": 99,
        "Church, Protestant__1": 28,
        "Church, Roman Catholic__1": 24,
        "Church, Christian Catholic__1": 24,
        "Canton__3": 0,
        "Commune__3": 0,
        "Church": 0,
        "Canton__4": 0,
        "Commune__4": 0,
        "Church__1": 0
      },
      {
        "Canton ID": 17,
        "Canton": "SG",
        "SFO Commune ID": 3256,
        "Commune": "Rüthi (SG)",
        "Canton__1": 115,
        "Commune__1": 129,
        "Church, Protestant": 28,
        "Church, Roman Catholic": 26,
        "Church, Christian Catholic": 24,
        "Canton__2": 115,
        "Commune__2": 129,
        "Church, Protestant__1": 28,
        "Church, Roman Catholic__1": 26,
        "Church, Christian Catholic__1": 24,
        "Canton__3": 0,
        "Commune__3": 0,
        "Church": 0,
        "Canton__4": 0,
        "Commune__4": 0,
        "Church__1": 0
      },
      {
        "Canton ID": 17,
        "Canton": "SG",
        "SFO Commune ID": 3296,
        "Commune": "Sargans",
        "Canton__1": 115,
        "Commune__1": 142,
        "Church, Protestant": 24,
        "Church, Roman Catholic": 21,
        "Church, Christian Catholic": 24,
        "Canton__2": 115,
        "Commune__2": 142,
        "Church, Protestant__1": 24,
        "Church, Roman Catholic__1": 21,
        "Church, Christian Catholic__1": 24,
        "Canton__3": 0,
        "Commune__3": 0,
        "Church": 0,
        "Canton__4": 0,
        "Commune__4": 0,
        "Church__1": 0
      },
      {
        "Canton ID": 17,
        "Canton": "SG",
        "SFO Commune ID": 3338,
        "Commune": "Schmerikon",
        "Canton__1": 115,
        "Commune__1": 119,
        "Church, Protestant": 24,
        "Church, Roman Catholic": 20,
        "Church, Christian Catholic": 24,
        "Canton__2": 115,
        "Commune__2": 119,
        "Church, Protestant__1": 24,
        "Church, Roman Catholic__1": 20,
        "Church, Christian Catholic__1": 24,
        "Canton__3": 0,
        "Commune__3": 0,
        "Church": 0,
        "Canton__4": 0,
        "Commune__4": 0,
        "Church__1": 0
      },
      {
        "Canton ID": 17,
        "Canton": "SG",
        "SFO Commune ID": 3315,
        "Commune": "Schänis",
        "Canton__1": 115,
        "Commune__1": 129,
        "Church, Protestant": 22.5,
        "Church, Roman Catholic": 25,
        "Church, Christian Catholic": 24,
        "Canton__2": 115,
        "Commune__2": 129,
        "Church, Protestant__1": 22.5,
        "Church, Roman Catholic__1": 25,
        "Church, Christian Catholic__1": 24,
        "Canton__3": 0,
        "Commune__3": 0,
        "Church": 0,
        "Canton__4": 0,
        "Commune__4": 0,
        "Church__1": 0
      },
      {
        "Canton ID": 17,
        "Canton": "SG",
        "SFO Commune ID": 3274,
        "Commune": "Sennwald",
        "Canton__1": 115,
        "Commune__1": 93,
        "Church, Protestant": 28,
        "Church, Roman Catholic": 18,
        "Church, Christian Catholic": 24,
        "Canton__2": 115,
        "Commune__2": 93,
        "Church, Protestant__1": 28,
        "Church, Roman Catholic__1": 18,
        "Church, Christian Catholic__1": 24,
        "Canton__3": 0,
        "Commune__3": 0,
        "Church": 0,
        "Canton__4": 0,
        "Commune__4": 0,
        "Church__1": 0
      },
      {
        "Canton ID": 17,
        "Canton": "SG",
        "SFO Commune ID": 3275,
        "Commune": "Sevelen",
        "Canton__1": 115,
        "Commune__1": 125,
        "Church, Protestant": 27,
        "Church, Roman Catholic": 20,
        "Church, Christian Catholic": 24,
        "Canton__2": 115,
        "Commune__2": 125,
        "Church, Protestant__1": 27,
        "Church, Roman Catholic__1": 20,
        "Church, Christian Catholic__1": 24,
        "Canton__3": 0,
        "Commune__3": 0,
        "Church": 0,
        "Canton__4": 0,
        "Commune__4": 0,
        "Church__1": 0
      },
      {
        "Canton ID": 17,
        "Canton": "SG",
        "SFO Commune ID": 3203,
        "Commune": "St. Gallen",
        "Canton__1": 115,
        "Commune__1": 141,
        "Church, Protestant": 26,
        "Church, Roman Catholic": 26,
        "Church, Christian Catholic": 24,
        "Canton__2": 115,
        "Commune__2": 141,
        "Church, Protestant__1": 26,
        "Church, Roman Catholic__1": 26,
        "Church, Christian Catholic__1": 24,
        "Canton__3": 0,
        "Commune__3": 0,
        "Church": 0,
        "Canton__4": 0,
        "Commune__4": 0,
        "Church__1": 0
      },
      {
        "Canton ID": 17,
        "Canton": "SG",
        "SFO Commune ID": 3236,
        "Commune": "St. Margrethen",
        "Canton__1": 115,
        "Commune__1": 117,
        "Church, Protestant": 28,
        "Church, Roman Catholic": 24,
        "Church, Christian Catholic": 24,
        "Canton__2": 115,
        "Commune__2": 117,
        "Church, Protestant__1": 28,
        "Church, Roman Catholic__1": 24,
        "Church, Christian Catholic__1": 24,
        "Canton__3": 0,
        "Commune__3": 0,
        "Church": 0,
        "Canton__4": 0,
        "Commune__4": 0,
        "Church__1": 0
      },
      {
        "Canton ID": 17,
        "Canton": "SG",
        "SFO Commune ID": 3217,
        "Commune": "Steinach",
        "Canton__1": 115,
        "Commune__1": 115,
        "Church, Protestant": 23,
        "Church, Roman Catholic": 27,
        "Church, Christian Catholic": 24,
        "Canton__2": 115,
        "Commune__2": 115,
        "Church, Protestant__1": 23,
        "Church, Roman Catholic__1": 27,
        "Church, Christian Catholic__1": 24,
        "Canton__3": 0,
        "Commune__3": 0,
        "Church": 0,
        "Canton__4": 0,
        "Commune__4": 0,
        "Church__1": 0
      },
      {
        "Canton ID": 17,
        "Canton": "SG",
        "SFO Commune ID": 3237,
        "Commune": "Thal",
        "Canton__1": 115,
        "Commune__1": 94,
        "Church, Protestant": 28,
        "Church, Roman Catholic": 27,
        "Church, Christian Catholic": 24,
        "Canton__2": 115,
        "Commune__2": 94,
        "Church, Protestant__1": 28,
        "Church, Roman Catholic__1": 27,
        "Church, Christian Catholic__1": 24,
        "Canton__3": 0,
        "Commune__3": 0,
        "Church": 0,
        "Canton__4": 0,
        "Commune__4": 0,
        "Church__1": 0
      },
      {
        "Canton ID": 17,
        "Canton": "SG",
        "SFO Commune ID": 3218,
        "Commune": "Tübach",
        "Canton__1": 115,
        "Commune__1": 82,
        "Church, Protestant": 23,
        "Church, Roman Catholic": 23,
        "Church, Christian Catholic": 24,
        "Canton__2": 115,
        "Commune__2": 82,
        "Church, Protestant__1": 23,
        "Church, Roman Catholic__1": 23,
        "Church, Christian Catholic__1": 24,
        "Canton__3": 0,
        "Commune__3": 0,
        "Church": 0,
        "Canton__4": 0,
        "Commune__4": 0,
        "Church__1": 0
      },
      {
        "Canton ID": 17,
        "Canton": "SG",
        "SFO Commune ID": 3219,
        "Commune": "Untereggen",
        "Canton__1": 115,
        "Commune__1": 119,
        "Church, Protestant": 23,
        "Church, Roman Catholic": 24,
        "Church, Christian Catholic": 24,
        "Canton__2": 115,
        "Commune__2": 119,
        "Church, Protestant__1": 23,
        "Church, Roman Catholic__1": 24,
        "Church, Christian Catholic__1": 24,
        "Canton__3": 0,
        "Commune__3": 0,
        "Church": 0,
        "Canton__4": 0,
        "Commune__4": 0,
        "Church__1": 0
      },
      {
        "Canton ID": 17,
        "Canton": "SG",
        "SFO Commune ID": 3339,
        "Commune": "Uznach",
        "Canton__1": 115,
        "Commune__1": 122,
        "Church, Protestant": 24,
        "Church, Roman Catholic": 26,
        "Church, Christian Catholic": 24,
        "Canton__2": 115,
        "Commune__2": 122,
        "Church, Protestant__1": 24,
        "Church, Roman Catholic__1": 26,
        "Church, Christian Catholic__1": 24,
        "Canton__3": 0,
        "Commune__3": 0,
        "Church": 0,
        "Canton__4": 0,
        "Commune__4": 0,
        "Church__1": 0
      },
      {
        "Canton ID": 17,
        "Canton": "SG",
        "SFO Commune ID": 3408,
        "Commune": "Uzwil",
        "Canton__1": 115,
        "Commune__1": 133,
        "Church, Protestant": 25,
        "Church, Roman Catholic": 23,
        "Church, Christian Catholic": 24,
        "Canton__2": 115,
        "Commune__2": 133,
        "Church, Protestant__1": 25,
        "Church, Roman Catholic__1": 23,
        "Church, Christian Catholic__1": 24,
        "Canton__3": 0,
        "Commune__3": 0,
        "Church": 0,
        "Canton__4": 0,
        "Commune__4": 0,
        "Church__1": 0
      },
      {
        "Canton ID": 17,
        "Canton": "SG",
        "SFO Commune ID": 3297,
        "Commune": "Vilters-Wangs",
        "Canton__1": 115,
        "Commune__1": 136,
        "Church, Protestant": 24,
        "Church, Roman Catholic": 24,
        "Church, Christian Catholic": 24,
        "Canton__2": 115,
        "Commune__2": 136,
        "Church, Protestant__1": 24,
        "Church, Roman Catholic__1": 24,
        "Church, Christian Catholic__1": 24,
        "Canton__3": 0,
        "Commune__3": 0,
        "Church": 0,
        "Canton__4": 0,
        "Commune__4": 0,
        "Church__1": 0
      },
      {
        "Canton ID": 17,
        "Canton": "SG",
        "SFO Commune ID": 3444,
        "Commune": "Waldkirch",
        "Canton__1": 115,
        "Commune__1": 125,
        "Church, Protestant": 28,
        "Church, Roman Catholic": 26,
        "Church, Christian Catholic": 24,
        "Canton__2": 115,
        "Commune__2": 125,
        "Church, Protestant__1": 28,
        "Church, Roman Catholic__1": 26,
        "Church, Christian Catholic__1": 24,
        "Canton__3": 0,
        "Commune__3": 0,
        "Church": 0,
        "Canton__4": 0,
        "Commune__4": 0,
        "Church__1": 0
      },
      {
        "Canton ID": 17,
        "Canton": "SG",
        "SFO Commune ID": 3298,
        "Commune": "Walenstadt",
        "Canton__1": 115,
        "Commune__1": 122,
        "Church, Protestant": 24,
        "Church, Roman Catholic": 24,
        "Church, Christian Catholic": 24,
        "Canton__2": 115,
        "Commune__2": 122,
        "Church, Protestant__1": 24,
        "Church, Roman Catholic__1": 24,
        "Church, Christian Catholic__1": 24,
        "Canton__3": 0,
        "Commune__3": 0,
        "Church": 0,
        "Canton__4": 0,
        "Commune__4": 0,
        "Church__1": 0
      },
      {
        "Canton ID": 17,
        "Canton": "SG",
        "SFO Commune ID": 3276,
        "Commune": "Wartau",
        "Canton__1": 115,
        "Commune__1": 160,
        "Church, Protestant": 28,
        "Church, Roman Catholic": 22,
        "Church, Christian Catholic": 24,
        "Canton__2": 115,
        "Commune__2": 160,
        "Church, Protestant__1": 28,
        "Church, Roman Catholic__1": 22,
        "Church, Christian Catholic__1": 24,
        "Canton__3": 0,
        "Commune__3": 0,
        "Church": 0,
        "Canton__4": 0,
        "Commune__4": 0,
        "Church__1": 0
      },
      {
        "Canton ID": 17,
        "Canton": "SG",
        "SFO Commune ID": 3379,
        "Commune": "Wattwil",
        "Canton__1": 115,
        "Commune__1": 135,
        "Church, Protestant": 28,
        "Church, Roman Catholic": 26,
        "Church, Christian Catholic": 24,
        "Canton__2": 115,
        "Commune__2": 135,
        "Church, Protestant__1": 28,
        "Church, Roman Catholic__1": 26,
        "Church, Christian Catholic__1": 24,
        "Canton__3": 0,
        "Commune__3": 0,
        "Church": 0,
        "Canton__4": 0,
        "Commune__4": 0,
        "Church__1": 0
      },
      {
        "Canton ID": 17,
        "Canton": "SG",
        "SFO Commune ID": 3316,
        "Commune": "Weesen",
        "Canton__1": 115,
        "Commune__1": 130,
        "Church, Protestant": 27,
        "Church, Roman Catholic": 26,
        "Church, Christian Catholic": 24,
        "Canton__2": 115,
        "Commune__2": 130,
        "Church, Protestant__1": 27,
        "Church, Roman Catholic__1": 26,
        "Church, Christian Catholic__1": 24,
        "Canton__3": 0,
        "Commune__3": 0,
        "Church": 0,
        "Canton__4": 0,
        "Commune__4": 0,
        "Church__1": 0
      },
      {
        "Canton ID": 17,
        "Canton": "SG",
        "SFO Commune ID": 3238,
        "Commune": "Widnau",
        "Canton__1": 115,
        "Commune__1": 86,
        "Church, Protestant": 24,
        "Church, Roman Catholic": 17,
        "Church, Christian Catholic": 24,
        "Canton__2": 115,
        "Commune__2": 86,
        "Church, Protestant__1": 24,
        "Church, Roman Catholic__1": 17,
        "Church, Christian Catholic__1": 24,
        "Canton__3": 0,
        "Commune__3": 0,
        "Church": 0,
        "Canton__4": 0,
        "Commune__4": 0,
        "Church__1": 0
      },
      {
        "Canton ID": 17,
        "Canton": "SG",
        "SFO Commune ID": 3427,
        "Commune": "Wil (SG)",
        "Canton__1": 115,
        "Commune__1": 118,
        "Church, Protestant": 23,
        "Church, Roman Catholic": 22,
        "Church, Christian Catholic": 24,
        "Canton__2": 115,
        "Commune__2": 118,
        "Church, Protestant__1": 23,
        "Church, Roman Catholic__1": 22,
        "Church, Christian Catholic__1": 24,
        "Canton__3": 0,
        "Commune__3": 0,
        "Church": 0,
        "Canton__4": 0,
        "Commune__4": 0,
        "Church__1": 0
      },
      {
        "Canton ID": 17,
        "Canton": "SG",
        "SFO Commune ID": 3359,
        "Commune": "Wildhaus-Alt St. Johann",
        "Canton__1": 115,
        "Commune__1": 138,
        "Church, Protestant": 28,
        "Church, Roman Catholic": 26,
        "Church, Christian Catholic": 24,
        "Canton__2": 115,
        "Commune__2": 138,
        "Church, Protestant__1": 28,
        "Church, Roman Catholic__1": 26,
        "Church, Christian Catholic__1": 24,
        "Canton__3": 0,
        "Commune__3": 0,
        "Church": 0,
        "Canton__4": 0,
        "Commune__4": 0,
        "Church__1": 0
      },
      {
        "Canton ID": 17,
        "Canton": "SG",
        "SFO Commune ID": 3204,
        "Commune": "Wittenbach",
        "Canton__1": 115,
        "Commune__1": 135,
        "Church, Protestant": 25,
        "Church, Roman Catholic": 24,
        "Church, Christian Catholic": 24,
        "Canton__2": 115,
        "Commune__2": 135,
        "Church, Protestant__1": 25,
        "Church, Roman Catholic__1": 24,
        "Church, Christian Catholic__1": 24,
        "Canton__3": 0,
        "Commune__3": 0,
        "Church": 0,
        "Canton__4": 0,
        "Commune__4": 0,
        "Church__1": 0
      },
      {
        "Canton ID": 17,
        "Canton": "SG",
        "SFO Commune ID": 3426,
        "Commune": "Zuzwil (SG)",
        "Canton__1": 115,
        "Commune__1": 87,
        "Church, Protestant": 23,
        "Church, Roman Catholic": 21,
        "Church, Christian Catholic": 24,
        "Canton__2": 115,
        "Commune__2": 87,
        "Church, Protestant__1": 23,
        "Church, Roman Catholic__1": 21,
        "Church, Christian Catholic__1": 24,
        "Canton__3": 0,
        "Commune__3": 0,
        "Church": 0,
        "Canton__4": 0,
        "Commune__4": 0,
        "Church__1": 0
      }
    ]
  ]
}